[
  {
    "document1": "document0001.txt",
    "document2": "document0018.txt",
    "score": 0.5390308282809808
  },
  {
    "document1": "document0002.txt",
    "document2": "document0035.txt",
    "score": 0.5239921391443453
  },
  {
    "document1": "document0003.txt",
    "document2": "document0057.txt",
    "score": 0.5146340751870211
  },
  {
    "document1": "document0011.txt",
    "document2": "document0017.txt",
    "score": 0.5134934460688314
  },
  {
    "document1": "document0011.txt",
    "document2": "document0019.txt",
    "score": 0.5014613170146769
  },
  {
    "document1": "document0013.txt",
    "document2": "document0057.txt",
    "score": 0.5343805597502228
  },
  {
    "document1": "document0015.txt",
    "document2": "document0023.txt",
    "score": 0.5319563494383448
  },
  {
    "document1": "document0015.txt",
    "document2": "document0045.txt",
    "score": 0.5119580772694772
  },
  {
    "document1": "document0016.txt",
    "document2": "document0024.txt",
    "score": 0.50131330462726
  },
  {
    "document1": "document0016.txt",
    "document2": "document0028.txt",
    "score": 0.5113854632851478
  },
  {
    "document1": "document0016.txt",
    "document2": "document0041.txt",
    "score": 0.5242490227398575
  },
  {
    "document1": "document0017.txt",
    "document2": "document0020.txt",
    "score": 0.5138258504858292
  },
  {
    "document1": "document0017.txt",
    "document2": "document0027.txt",
    "score": 0.5286442743799318
  },
  {
    "document1": "document0017.txt",
    "document2": "document0056.txt",
    "score": 0.5042642906618211
  },
  {
    "document1": "document0018.txt",
    "document2": "document0032.txt",
    "score": 0.5004845160388092
  },
  {
    "document1": "document0018.txt",
    "document2": "document0053.txt",
    "score": 0.5323828089592695
  },
  {
    "document1": "document0020.txt",
    "document2": "document0030.txt",
    "score": 0.5234251344290941
  },
  {
    "document1": "document0020.txt",
    "document2": "document0040.txt",
    "score": 0.5229031543016631
  },
  {
    "document1": "document0021.txt",
    "document2": "document0049.txt",
    "score": 0.5342650354943244
  },
  {
    "document1": "document0022.txt",
    "document2": "document0027.txt",
    "score": 0.5146267158453242
  },
  {
    "document1": "document0024.txt",
    "document2": "document0032.txt",
    "score": 0.5043576205774462
  },
  {
    "document1": "document0024.txt",
    "document2": "document0034.txt",
    "score": 0.5306234898527131
  },
  {
    "document1": "document0025.txt",
    "document2": "document0030.txt",
    "score": 0.5075544633680364
  },
  {
    "document1": "document0025.txt",
    "document2": "document0032.txt",
    "score": 0.5362209066815906
  },
  {
    "document1": "document0026.txt",
    "document2": "document0044.txt",
    "score": 0.5241195786758982
  },
  {
    "document1": "document0027.txt",
    "document2": "document0048.txt",
    "score": 0.5245691514255103
  },
  {
    "document1": "document0027.txt",
    "document2": "document0049.txt",
    "score": 0.5210117935009992
  },
  {
    "document1": "document0028.txt",
    "document2": "document0055.txt",
    "score": 0.5365449255979462
  },
  {
    "document1": "document0029.txt",
    "document2": "document0037.txt",
    "score": 0.501677746705939
  },
  {
    "document1": "document0031.txt",
    "document2": "document0047.txt",
    "score": 0.5022377163235064
  },
  {
    "document1": "document0033.txt",
    "document2": "document0037.txt",
    "score": 0.5266570630861551
  },
  {
    "document1": "document0036.txt",
    "document2": "document0046.txt",
    "score": 0.5114100497010599
  },
  {
    "document1": "document0037.txt",
    "document2": "document0041.txt",
    "score": 0.5305491532971975
  },
  {
    "document1": "document0037.txt",
    "document2": "document0057.txt",
    "score": 0.5192818308813129
  },
  {
    "document1": "document0040.txt",
    "document2": "document0043.txt",
    "score": 0.5107916873017921
  },
  {
    "document1": "document0040.txt",
    "document2": "document0049.txt",
    "score": 0.5222830040596014
  },
  {
    "document1": "document0045.txt",
    "document2": "document0053.txt",
    "score": 0.5215244511620412
  },
  {
    "document1": "document0046.txt",
    "document2": "document0057.txt",
    "score": 0.5132588820562134
  },
  {
    "document1": "document0050.txt",
    "document2": "document0057.txt",
    "score": 0.5011675061333034
  }
]