[
  {
    "document1": "document0001.txt",
    "document2": "document0004.txt",
    "score": 1.1744704094308054
  },
  {
    "document1": "document0001.txt",
    "document2": "document0005.txt",
    "score": 0.7399429910071654
  },
  {
    "document1": "document0001.txt",
    "document2": "document0023.txt",
    "score": 0.8119639719715914
  },
  {
    "document1": "document0001.txt",
    "document2": "document0028.txt",
    "score": 0.8688962967889687
  },
  {
    "document1": "document0001.txt",
    "document2": "document0036.txt",
    "score": 0.877751053968787
  },
  {
    "document1": "document0001.txt",
    "document2": "document0047.txt",
    "score": 0.7025553731859402
  },
  {
    "document1": "document0001.txt",
    "document2": "document0048.txt",
    "score": 0.8585497951653892
  },
  {
    "document1": "document0001.txt",
    "document2": "document0057.txt",
    "score": 0.8175476003572647
  },
  {
    "document1": "document0002.txt",
    "document2": "document0014.txt",
    "score": 0.8708279390622994
  },
  {
    "document1": "document0002.txt",
    "document2": "document0023.txt",
    "score": 0.7080441431723801
  },
  {
    "document1": "document0002.txt",
    "document2": "document0025.txt",
    "score": 0.727843160167673
  },
  {
    "document1": "document0002.txt",
    "document2": "document0029.txt",
    "score": 0.8279058271104593
  },
  {
    "document1": "document0002.txt",
    "document2": "document0032.txt",
    "score": 0.704929836634623
  },
  {
    "document1": "document0002.txt",
    "document2": "document0036.txt",
    "score": 0.9383823945124178
  },
  {
    "document1": "document0002.txt",
    "document2": "document0042.txt",
    "score": 0.7695874798089613
  },
  {
    "document1": "document0002.txt",
    "document2": "document0044.txt",
    "score": 0.8307576891009069
  },
  {
    "document1": "document0002.txt",
    "document2": "document0047.txt",
    "score": 0.7973020703783014
  },
  {
    "document1": "document0002.txt",
    "document2": "document0053.txt",
    "score": 0.8389939987905953
  },
  {
    "document1": "document0002.txt",
    "document2": "document0054.txt",
    "score": 0.7802731473361229
  },
  {
    "document1": "document0003.txt",
    "document2": "document0013.txt",
    "score": 0.8211797049797784
  },
  {
    "document1": "document0003.txt",
    "document2": "document0014.txt",
    "score": 0.7611961135621781
  },
  {
    "document1": "document0003.txt",
    "document2": "document0024.txt",
    "score": 0.8074568419865836
  },
  {
    "document1": "document0003.txt",
    "document2": "document0027.txt",
    "score": 0.9262196708862459
  },
  {
    "document1": "document0003.txt",
    "document2": "document0034.txt",
    "score": 0.8336141472217294
  },
  {
    "document1": "document0003.txt",
    "document2": "document0038.txt",
    "score": 0.7368569069440067
  },
  {
    "document1": "document0003.txt",
    "document2": "document0041.txt",
    "score": 0.949549290556877
  },
  {
    "document1": "document0003.txt",
    "document2": "document0042.txt",
    "score": 0.77307718945775
  },
  {
    "document1": "document0003.txt",
    "document2": "document0044.txt",
    "score": 0.8473860072870255
  },
  {
    "document1": "document0003.txt",
    "document2": "document0046.txt",
    "score": 0.7682829260936545
  },
  {
    "document1": "document0003.txt",
    "document2": "document0048.txt",
    "score": 0.754757697086283
  },
  {
    "document1": "document0003.txt",
    "document2": "document0049.txt",
    "score": 0.8780226406036564
  },
  {
    "document1": "document0003.txt",
    "document2": "document0051.txt",
    "score": 0.7929376125006918
  },
  {
    "document1": "document0003.txt",
    "document2": "document0057.txt",
    "score": 0.8785628141365237
  },
  {
    "document1": "document0004.txt",
    "document2": "document0025.txt",
    "score": 0.7666124444180208
  },
  {
    "document1": "document0004.txt",
    "document2": "document0026.txt",
    "score": 0.8752119408582626
  },
  {
    "document1": "document0004.txt",
    "document2": "document0047.txt",
    "score": 0.8177106058500435
  },
  {
    "document1": "document0005.txt",
    "document2": "document0008.txt",
    "score": 0.702600540214042
  },
  {
    "document1": "document0005.txt",
    "document2": "document0021.txt",
    "score": 0.701968743896653
  },
  {
    "document1": "document0005.txt",
    "document2": "document0037.txt",
    "score": 0.7167194255451443
  },
  {
    "document1": "document0005.txt",
    "document2": "document0041.txt",
    "score": 0.7734891918141088
  },
  {
    "document1": "document0005.txt",
    "document2": "document0045.txt",
    "score": 0.8273540472766967
  },
  {
    "document1": "document0005.txt",
    "document2": "document0046.txt",
    "score": 0.7513391139596447
  },
  {
    "document1": "document0005.txt",
    "document2": "document0056.txt",
    "score": 0.7656957705793904
  },
  {
    "document1": "document0006.txt",
    "document2": "document0008.txt",
    "score": 0.811971811329611
  },
  {
    "document1": "document0006.txt",
    "document2": "document0009.txt",
    "score": 0.7939707873190922
  },
  {
    "document1": "document0006.txt",
    "document2": "document0010.txt",
    "score": 0.8616656225990167
  },
  {
    "document1": "document0006.txt",
    "document2": "document0016.txt",
    "score": 0.8406592908902729
  },
  {
    "document1": "document0006.txt",
    "document2": "document0019.txt",
    "score": 0.7281772596800316
  },
  {
    "document1": "document0006.txt",
    "document2": "document0023.txt",
    "score": 1.0466620222354484
  },
  {
    "document1": "document0006.txt",
    "document2": "document0030.txt",
    "score": 0.7581047680783214
  },
  {
    "document1": "document0006.txt",
    "document2": "document0050.txt",
    "score": 0.7660412818553838
  },
  {
    "document1": "document0006.txt",
    "document2": "document0051.txt",
    "score": 0.8464696405302703
  },
  {
    "document1": "document0006.txt",
    "document2": "document0057.txt",
    "score": 0.808712266730782
  },
  {
    "document1": "document0007.txt",
    "document2": "document0008.txt",
    "score": 0.8456713406576174
  },
  {
    "document1": "document0007.txt",
    "document2": "document0009.txt",
    "score": 0.833174347125347
  },
  {
    "document1": "document0007.txt",
    "document2": "document0033.txt",
    "score": 0.7950966215658974
  },
  {
    "document1": "document0007.txt",
    "document2": "document0038.txt",
    "score": 0.7246707689600845
  },
  {
    "document1": "document0007.txt",
    "document2": "document0041.txt",
    "score": 0.7152429601168759
  },
  {
    "document1": "document0007.txt",
    "document2": "document0050.txt",
    "score": 0.7608258599333068
  },
  {
    "document1": "document0008.txt",
    "document2": "document0016.txt",
    "score": 0.8800522469071731
  },
  {
    "document1": "document0008.txt",
    "document2": "document0020.txt",
    "score": 0.9711377487470528
  },
  {
    "document1": "document0008.txt",
    "document2": "document0023.txt",
    "score": 0.8513179737026555
  },
  {
    "document1": "document0008.txt",
    "document2": "document0034.txt",
    "score": 0.7185599582034025
  },
  {
    "document1": "document0009.txt",
    "document2": "document0010.txt",
    "score": 1.0189380531860748
  },
  {
    "document1": "document0009.txt",
    "document2": "document0011.txt",
    "score": 0.718814486095074
  },
  {
    "document1": "document0009.txt",
    "document2": "document0031.txt",
    "score": 0.9063128254197952
  },
  {
    "document1": "document0009.txt",
    "document2": "document0034.txt",
    "score": 0.9300237045963551
  },
  {
    "document1": "document0009.txt",
    "document2": "document0037.txt",
    "score": 0.8801811826539717
  },
  {
    "document1": "document0009.txt",
    "document2": "document0041.txt",
    "score": 0.7199347704358574
  },
  {
    "document1": "document0009.txt",
    "document2": "document0045.txt",
    "score": 0.9540440476345153
  },
  {
    "document1": "document0009.txt",
    "document2": "document0046.txt",
    "score": 0.8629827679403438
  },
  {
    "document1": "document0009.txt",
    "document2": "document0056.txt",
    "score": 0.8807236695268061
  },
  {
    "document1": "document0010.txt",
    "document2": "document0011.txt",
    "score": 0.8237147241358006
  },
  {
    "document1": "document0010.txt",
    "document2": "document0016.txt",
    "score": 1.0094950521725834
  },
  {
    "document1": "document0010.txt",
    "document2": "document0019.txt",
    "score": 0.7865817971065449
  },
  {
    "document1": "document0010.txt",
    "document2": "document0022.txt",
    "score": 0.700670183734184
  },
  {
    "document1": "document0010.txt",
    "document2": "document0030.txt",
    "score": 0.7311468370500875
  },
  {
    "document1": "document0010.txt",
    "document2": "document0031.txt",
    "score": 0.733346024309143
  },
  {
    "document1": "document0010.txt",
    "document2": "document0039.txt",
    "score": 0.7673834344869996
  },
  {
    "document1": "document0010.txt",
    "document2": "document0045.txt",
    "score": 0.7165398944345619
  },
  {
    "document1": "document0010.txt",
    "document2": "document0050.txt",
    "score": 0.9045430957223025
  },
  {
    "document1": "document0010.txt",
    "document2": "document0056.txt",
    "score": 0.791466893683986
  },
  {
    "document1": "document0011.txt",
    "document2": "document0023.txt",
    "score": 0.7315859509705858
  },
  {
    "document1": "document0011.txt",
    "document2": "document0025.txt",
    "score": 0.8667399144807741
  },
  {
    "document1": "document0011.txt",
    "document2": "document0027.txt",
    "score": 0.9044553035105822
  },
  {
    "document1": "document0011.txt",
    "document2": "document0035.txt",
    "score": 0.7851382141106348
  },
  {
    "document1": "document0011.txt",
    "document2": "document0048.txt",
    "score": 0.8935239215613168
  },
  {
    "document1": "document0011.txt",
    "document2": "document0050.txt",
    "score": 0.8209575987719767
  },
  {
    "document1": "document0011.txt",
    "document2": "document0057.txt",
    "score": 1.0440834817056068
  },
  {
    "document1": "document0012.txt",
    "document2": "document0013.txt",
    "score": 0.7303391645905295
  },
  {
    "document1": "document0012.txt",
    "document2": "document0024.txt",
    "score": 0.7188185304127772
  },
  {
    "document1": "document0012.txt",
    "document2": "document0027.txt",
    "score": 0.8079273813336175
  },
  {
    "document1": "document0012.txt",
    "document2": "document0029.txt",
    "score": 0.7051648869417095
  },
  {
    "document1": "document0012.txt",
    "document2": "document0034.txt",
    "score": 0.7644218236432889
  },
  {
    "document1": "document0012.txt",
    "document2": "document0035.txt",
    "score": 0.7356626247330863
  },
  {
    "document1": "document0012.txt",
    "document2": "document0041.txt",
    "score": 0.8272201057197348
  },
  {
    "document1": "document0012.txt",
    "document2": "document0042.txt",
    "score": 0.833191072684874
  },
  {
    "document1": "document0012.txt",
    "document2": "document0046.txt",
    "score": 0.8487551610104577
  },
  {
    "document1": "document0012.txt",
    "document2": "document0051.txt",
    "score": 0.7121688481924323
  },
  {
    "document1": "document0012.txt",
    "document2": "document0057.txt",
    "score": 0.7989538416496694
  },
  {
    "document1": "document0013.txt",
    "document2": "document0014.txt",
    "score": 0.8718783168355957
  },
  {
    "document1": "document0013.txt",
    "document2": "document0015.txt",
    "score": 0.8077010499764381
  },
  {
    "document1": "document0013.txt",
    "document2": "document0018.txt",
    "score": 0.7783799383543234
  },
  {
    "document1": "document0013.txt",
    "document2": "document0021.txt",
    "score": 0.8450117345317626
  },
  {
    "document1": "document0013.txt",
    "document2": "document0035.txt",
    "score": 0.8986572270272595
  },
  {
    "document1": "document0013.txt",
    "document2": "document0036.txt",
    "score": 0.746129204363726
  },
  {
    "document1": "document0013.txt",
    "document2": "document0037.txt",
    "score": 0.8119028519794889
  },
  {
    "document1": "document0013.txt",
    "document2": "document0038.txt",
    "score": 0.8928276132253579
  },
  {
    "document1": "document0013.txt",
    "document2": "document0042.txt",
    "score": 0.8494602144138332
  },
  {
    "document1": "document0013.txt",
    "document2": "document0051.txt",
    "score": 0.8256734322014883
  },
  {
    "document1": "document0014.txt",
    "document2": "document0021.txt",
    "score": 0.7339329292997796
  },
  {
    "document1": "document0014.txt",
    "document2": "document0033.txt",
    "score": 0.8170758774959676
  },
  {
    "document1": "document0014.txt",
    "document2": "document0035.txt",
    "score": 0.7413730969613752
  },
  {
    "document1": "document0014.txt",
    "document2": "document0036.txt",
    "score": 0.7261780125591202
  },
  {
    "document1": "document0014.txt",
    "document2": "document0037.txt",
    "score": 0.7540789290461455
  },
  {
    "document1": "document0015.txt",
    "document2": "document0027.txt",
    "score": 0.8430639870351243
  },
  {
    "document1": "document0015.txt",
    "document2": "document0034.txt",
    "score": 0.8327983194590061
  },
  {
    "document1": "document0015.txt",
    "document2": "document0035.txt",
    "score": 0.9048716172362704
  },
  {
    "document1": "document0015.txt",
    "document2": "document0038.txt",
    "score": 0.7086157211909727
  },
  {
    "document1": "document0015.txt",
    "document2": "document0041.txt",
    "score": 0.8644571973520242
  },
  {
    "document1": "document0015.txt",
    "document2": "document0042.txt",
    "score": 0.9774032961033291
  },
  {
    "document1": "document0015.txt",
    "document2": "document0049.txt",
    "score": 0.9332483985884727
  },
  {
    "document1": "document0015.txt",
    "document2": "document0054.txt",
    "score": 0.7435961556529814
  },
  {
    "document1": "document0016.txt",
    "document2": "document0020.txt",
    "score": 1.06370913423859
  },
  {
    "document1": "document0016.txt",
    "document2": "document0038.txt",
    "score": 0.7651638203948866
  },
  {
    "document1": "document0016.txt",
    "document2": "document0050.txt",
    "score": 0.9643067472738286
  },
  {
    "document1": "document0016.txt",
    "document2": "document0051.txt",
    "score": 0.7197654008771988
  },
  {
    "document1": "document0016.txt",
    "document2": "document0056.txt",
    "score": 0.7067217386700394
  },
  {
    "document1": "document0017.txt",
    "document2": "document0026.txt",
    "score": 0.7327296587671736
  },
  {
    "document1": "document0017.txt",
    "document2": "document0052.txt",
    "score": 0.7020102466721599
  },
  {
    "document1": "document0018.txt",
    "document2": "document0024.txt",
    "score": 0.817130630514029
  },
  {
    "document1": "document0018.txt",
    "document2": "document0025.txt",
    "score": 0.7671681737298628
  },
  {
    "document1": "document0018.txt",
    "document2": "document0027.txt",
    "score": 0.7874162133429304
  },
  {
    "document1": "document0018.txt",
    "document2": "document0032.txt",
    "score": 0.7896403163446925
  },
  {
    "document1": "document0018.txt",
    "document2": "document0041.txt",
    "score": 0.8604169384824942
  },
  {
    "document1": "document0018.txt",
    "document2": "document0044.txt",
    "score": 0.8331250678849833
  },
  {
    "document1": "document0018.txt",
    "document2": "document0046.txt",
    "score": 0.8132806464439818
  },
  {
    "document1": "document0018.txt",
    "document2": "document0048.txt",
    "score": 0.7465821672612264
  },
  {
    "document1": "document0018.txt",
    "document2": "document0049.txt",
    "score": 0.7819200644141144
  },
  {
    "document1": "document0018.txt",
    "document2": "document0050.txt",
    "score": 0.8811908328459016
  },
  {
    "document1": "document0018.txt",
    "document2": "document0057.txt",
    "score": 0.8528308497796471
  },
  {
    "document1": "document0019.txt",
    "document2": "document0031.txt",
    "score": 0.8274529812050783
  },
  {
    "document1": "document0019.txt",
    "document2": "document0034.txt",
    "score": 0.8904316025260125
  },
  {
    "document1": "document0019.txt",
    "document2": "document0037.txt",
    "score": 0.9527148565471798
  },
  {
    "document1": "document0019.txt",
    "document2": "document0041.txt",
    "score": 0.9674681677328982
  },
  {
    "document1": "document0019.txt",
    "document2": "document0045.txt",
    "score": 0.9926835142045616
  },
  {
    "document1": "document0019.txt",
    "document2": "document0046.txt",
    "score": 0.8465230211718952
  },
  {
    "document1": "document0019.txt",
    "document2": "document0056.txt",
    "score": 0.8323517329563643
  },
  {
    "document1": "document0020.txt",
    "document2": "document0022.txt",
    "score": 0.7131551481657038
  },
  {
    "document1": "document0020.txt",
    "document2": "document0025.txt",
    "score": 0.8388243669674703
  },
  {
    "document1": "document0020.txt",
    "document2": "document0029.txt",
    "score": 0.7863325225452156
  },
  {
    "document1": "document0020.txt",
    "document2": "document0036.txt",
    "score": 0.7236287298458136
  },
  {
    "document1": "document0020.txt",
    "document2": "document0039.txt",
    "score": 0.7258450447979852
  },
  {
    "document1": "document0020.txt",
    "document2": "document0042.txt",
    "score": 1.02545667376992
  },
  {
    "document1": "document0020.txt",
    "document2": "document0046.txt",
    "score": 0.8910905930860025
  },
  {
    "document1": "document0020.txt",
    "document2": "document0054.txt",
    "score": 0.7091337964349407
  },
  {
    "document1": "document0021.txt",
    "document2": "document0024.txt",
    "score": 0.7583304836516005
  },
  {
    "document1": "document0021.txt",
    "document2": "document0025.txt",
    "score": 0.7473972075245906
  },
  {
    "document1": "document0021.txt",
    "document2": "document0027.txt",
    "score": 0.8641418686001938
  },
  {
    "document1": "document0021.txt",
    "document2": "document0030.txt",
    "score": 0.7398501774402435
  },
  {
    "document1": "document0021.txt",
    "document2": "document0032.txt",
    "score": 0.7011069202911535
  },
  {
    "document1": "document0021.txt",
    "document2": "document0033.txt",
    "score": 0.7046928162828137
  },
  {
    "document1": "document0021.txt",
    "document2": "document0038.txt",
    "score": 0.9052545355577822
  },
  {
    "document1": "document0021.txt",
    "document2": "document0041.txt",
    "score": 0.9747189613228208
  },
  {
    "document1": "document0021.txt",
    "document2": "document0042.txt",
    "score": 0.753408923413639
  },
  {
    "document1": "document0021.txt",
    "document2": "document0044.txt",
    "score": 0.882492012656362
  },
  {
    "document1": "document0021.txt",
    "document2": "document0045.txt",
    "score": 0.7519729882954268
  },
  {
    "document1": "document0021.txt",
    "document2": "document0046.txt",
    "score": 0.7654072857882792
  },
  {
    "document1": "document0021.txt",
    "document2": "document0049.txt",
    "score": 0.8738181065581866
  },
  {
    "document1": "document0021.txt",
    "document2": "document0050.txt",
    "score": 0.9125920286536473
  },
  {
    "document1": "document0021.txt",
    "document2": "document0053.txt",
    "score": 0.7440429974347198
  },
  {
    "document1": "document0021.txt",
    "document2": "document0054.txt",
    "score": 0.9557446633108376
  },
  {
    "document1": "document0021.txt",
    "document2": "document0057.txt",
    "score": 0.873844964135156
  },
  {
    "document1": "document0022.txt",
    "document2": "document0026.txt",
    "score": 0.7670766793803679
  },
  {
    "document1": "document0022.txt",
    "document2": "document0031.txt",
    "score": 0.8665177739654574
  },
  {
    "document1": "document0022.txt",
    "document2": "document0034.txt",
    "score": 0.7885655941585019
  },
  {
    "document1": "document0022.txt",
    "document2": "document0037.txt",
    "score": 0.9084900770177662
  },
  {
    "document1": "document0022.txt",
    "document2": "document0041.txt",
    "score": 0.8121930340982166
  },
  {
    "document1": "document0022.txt",
    "document2": "document0045.txt",
    "score": 0.922599153849061
  },
  {
    "document1": "document0022.txt",
    "document2": "document0046.txt",
    "score": 0.8546819468746798
  },
  {
    "document1": "document0022.txt",
    "document2": "document0056.txt",
    "score": 0.8455472418710802
  },
  {
    "document1": "document0023.txt",
    "document2": "document0025.txt",
    "score": 0.934186232789049
  },
  {
    "document1": "document0023.txt",
    "document2": "document0031.txt",
    "score": 0.9184147079748194
  },
  {
    "document1": "document0023.txt",
    "document2": "document0036.txt",
    "score": 0.7092177357787182
  },
  {
    "document1": "document0023.txt",
    "document2": "document0037.txt",
    "score": 0.9503714627492548
  },
  {
    "document1": "document0023.txt",
    "document2": "document0042.txt",
    "score": 0.8661915090193109
  },
  {
    "document1": "document0023.txt",
    "document2": "document0046.txt",
    "score": 0.8805541173399763
  },
  {
    "document1": "document0023.txt",
    "document2": "document0054.txt",
    "score": 0.7063610890546391
  },
  {
    "document1": "document0024.txt",
    "document2": "document0030.txt",
    "score": 0.8680857343636664
  },
  {
    "document1": "document0024.txt",
    "document2": "document0038.txt",
    "score": 0.7294453611734966
  },
  {
    "document1": "document0024.txt",
    "document2": "document0041.txt",
    "score": 0.7205411442690762
  },
  {
    "document1": "document0024.txt",
    "document2": "document0050.txt",
    "score": 0.8834365160700066
  },
  {
    "document1": "document0025.txt",
    "document2": "document0034.txt",
    "score": 0.9932116528118862
  },
  {
    "document1": "document0025.txt",
    "document2": "document0035.txt",
    "score": 0.9298684832341967
  },
  {
    "document1": "document0025.txt",
    "document2": "document0037.txt",
    "score": 0.7194866386330231
  },
  {
    "document1": "document0025.txt",
    "document2": "document0044.txt",
    "score": 0.9502659872740076
  },
  {
    "document1": "document0025.txt",
    "document2": "document0056.txt",
    "score": 0.7023768793467355
  },
  {
    "document1": "document0026.txt",
    "document2": "document0028.txt",
    "score": 0.8167995052513172
  },
  {
    "document1": "document0026.txt",
    "document2": "document0048.txt",
    "score": 0.8498531290257882
  },
  {
    "document1": "document0027.txt",
    "document2": "document0041.txt",
    "score": 0.8411007323306431
  },
  {
    "document1": "document0027.txt",
    "document2": "document0046.txt",
    "score": 0.8549414250658448
  },
  {
    "document1": "document0027.txt",
    "document2": "document0047.txt",
    "score": 0.711678308670044
  },
  {
    "document1": "document0027.txt",
    "document2": "document0055.txt",
    "score": 0.7450568676697797
  },
  {
    "document1": "document0027.txt",
    "document2": "document0056.txt",
    "score": 0.8622251270344787
  },
  {
    "document1": "document0029.txt",
    "document2": "document0036.txt",
    "score": 0.9023134680989028
  },
  {
    "document1": "document0029.txt",
    "document2": "document0044.txt",
    "score": 0.850821205333813
  },
  {
    "document1": "document0029.txt",
    "document2": "document0047.txt",
    "score": 0.9344038260595863
  },
  {
    "document1": "document0029.txt",
    "document2": "document0057.txt",
    "score": 0.714301986927554
  },
  {
    "document1": "document0030.txt",
    "document2": "document0031.txt",
    "score": 0.8653634631774462
  },
  {
    "document1": "document0030.txt",
    "document2": "document0037.txt",
    "score": 0.7909445774333413
  },
  {
    "document1": "document0030.txt",
    "document2": "document0056.txt",
    "score": 0.8831832672792467
  },
  {
    "document1": "document0031.txt",
    "document2": "document0032.txt",
    "score": 0.8081796658080797
  },
  {
    "document1": "document0031.txt",
    "document2": "document0038.txt",
    "score": 0.8117586602509524
  },
  {
    "document1": "document0031.txt",
    "document2": "document0039.txt",
    "score": 0.8542138912401454
  },
  {
    "document1": "document0031.txt",
    "document2": "document0045.txt",
    "score": 0.7245100885228417
  },
  {
    "document1": "document0031.txt",
    "document2": "document0048.txt",
    "score": 1.0002333402370773
  },
  {
    "document1": "document0031.txt",
    "document2": "document0050.txt",
    "score": 0.9702158223524213
  },
  {
    "document1": "document0031.txt",
    "document2": "document0057.txt",
    "score": 0.8736461076549029
  },
  {
    "document1": "document0032.txt",
    "document2": "document0034.txt",
    "score": 0.743579749690963
  },
  {
    "document1": "document0032.txt",
    "document2": "document0035.txt",
    "score": 0.7479831706677077
  },
  {
    "document1": "document0032.txt",
    "document2": "document0037.txt",
    "score": 0.8594687882006334
  },
  {
    "document1": "document0032.txt",
    "document2": "document0038.txt",
    "score": 0.9076375381525174
  },
  {
    "document1": "document0032.txt",
    "document2": "document0041.txt",
    "score": 0.7221011193502919
  },
  {
    "document1": "document0032.txt",
    "document2": "document0042.txt",
    "score": 0.8988820848893034
  },
  {
    "document1": "document0032.txt",
    "document2": "document0044.txt",
    "score": 0.7430444832941298
  },
  {
    "document1": "document0032.txt",
    "document2": "document0046.txt",
    "score": 0.8361395350391202
  },
  {
    "document1": "document0032.txt",
    "document2": "document0048.txt",
    "score": 0.7486420820553611
  },
  {
    "document1": "document0032.txt",
    "document2": "document0057.txt",
    "score": 0.8821604934689843
  },
  {
    "document1": "document0033.txt",
    "document2": "document0035.txt",
    "score": 0.7678483155316884
  },
  {
    "document1": "document0033.txt",
    "document2": "document0041.txt",
    "score": 0.7477207265063868
  },
  {
    "document1": "document0033.txt",
    "document2": "document0042.txt",
    "score": 0.7848324719991184
  },
  {
    "document1": "document0033.txt",
    "document2": "document0044.txt",
    "score": 0.7326643862061227
  },
  {
    "document1": "document0033.txt",
    "document2": "document0049.txt",
    "score": 0.8899120190678145
  },
  {
    "document1": "document0034.txt",
    "document2": "document0035.txt",
    "score": 0.9044730500535633
  },
  {
    "document1": "document0034.txt",
    "document2": "document0038.txt",
    "score": 1.0164587710355701
  },
  {
    "document1": "document0034.txt",
    "document2": "document0039.txt",
    "score": 0.8201319671588865
  },
  {
    "document1": "document0034.txt",
    "document2": "document0041.txt",
    "score": 0.9389666055716117
  },
  {
    "document1": "document0034.txt",
    "document2": "document0042.txt",
    "score": 0.7346225286513886
  },
  {
    "document1": "document0034.txt",
    "document2": "document0046.txt",
    "score": 0.8789146610304621
  },
  {
    "document1": "document0034.txt",
    "document2": "document0047.txt",
    "score": 0.7453929989347872
  },
  {
    "document1": "document0034.txt",
    "document2": "document0050.txt",
    "score": 0.8569768482802432
  },
  {
    "document1": "document0034.txt",
    "document2": "document0053.txt",
    "score": 0.8614914549180711
  },
  {
    "document1": "document0034.txt",
    "document2": "document0054.txt",
    "score": 0.972299108298584
  },
  {
    "document1": "document0035.txt",
    "document2": "document0037.txt",
    "score": 0.7456259553211244
  },
  {
    "document1": "document0035.txt",
    "document2": "document0049.txt",
    "score": 0.7846979556611885
  },
  {
    "document1": "document0035.txt",
    "document2": "document0051.txt",
    "score": 0.9166536737987964
  },
  {
    "document1": "document0035.txt",
    "document2": "document0056.txt",
    "score": 0.8205881705867568
  },
  {
    "document1": "document0036.txt",
    "document2": "document0040.txt",
    "score": 0.9111343800626718
  },
  {
    "document1": "document0036.txt",
    "document2": "document0047.txt",
    "score": 0.7399365332579354
  },
  {
    "document1": "document0037.txt",
    "document2": "document0038.txt",
    "score": 0.8085309579277957
  },
  {
    "document1": "document0037.txt",
    "document2": "document0039.txt",
    "score": 0.8756588845560528
  },
  {
    "document1": "document0037.txt",
    "document2": "document0042.txt",
    "score": 0.7001387388914275
  },
  {
    "document1": "document0037.txt",
    "document2": "document0048.txt",
    "score": 1.0367950806606716
  },
  {
    "document1": "document0037.txt",
    "document2": "document0049.txt",
    "score": 0.9823775412465853
  },
  {
    "document1": "document0037.txt",
    "document2": "document0050.txt",
    "score": 0.8522417208592744
  },
  {
    "document1": "document0037.txt",
    "document2": "document0053.txt",
    "score": 0.804725761000034
  },
  {
    "document1": "document0037.txt",
    "document2": "document0054.txt",
    "score": 0.8456235197828993
  },
  {
    "document1": "document0037.txt",
    "document2": "document0057.txt",
    "score": 0.8339400822092485
  },
  {
    "document1": "document0038.txt",
    "document2": "document0046.txt",
    "score": 0.7250983860979388
  },
  {
    "document1": "document0038.txt",
    "document2": "document0056.txt",
    "score": 0.7991739682420335
  },
  {
    "document1": "document0039.txt",
    "document2": "document0041.txt",
    "score": 0.8479190676678843
  },
  {
    "document1": "document0039.txt",
    "document2": "document0045.txt",
    "score": 0.8396759008507398
  },
  {
    "document1": "document0039.txt",
    "document2": "document0056.txt",
    "score": 0.8144047956911852
  },
  {
    "document1": "document0040.txt",
    "document2": "document0045.txt",
    "score": 0.7088578365425527
  },
  {
    "document1": "document0041.txt",
    "document2": "document0046.txt",
    "score": 0.7355367132212189
  },
  {
    "document1": "document0042.txt",
    "document2": "document0046.txt",
    "score": 0.7961295654614555
  },
  {
    "document1": "document0042.txt",
    "document2": "document0051.txt",
    "score": 0.7267260477820627
  },
  {
    "document1": "document0042.txt",
    "document2": "document0056.txt",
    "score": 0.7712736006784846
  },
  {
    "document1": "document0044.txt",
    "document2": "document0047.txt",
    "score": 0.7547201127803694
  },
  {
    "document1": "document0044.txt",
    "document2": "document0048.txt",
    "score": 0.9099915122560223
  },
  {
    "document1": "document0044.txt",
    "document2": "document0053.txt",
    "score": 0.8276386605478102
  },
  {
    "document1": "document0044.txt",
    "document2": "document0054.txt",
    "score": 0.8669027634103588
  },
  {
    "document1": "document0044.txt",
    "document2": "document0057.txt",
    "score": 0.8618514940896652
  },
  {
    "document1": "document0045.txt",
    "document2": "document0056.txt",
    "score": 0.8334834427620011
  },
  {
    "document1": "document0046.txt",
    "document2": "document0047.txt",
    "score": 0.8044321806255562
  },
  {
    "document1": "document0046.txt",
    "document2": "document0048.txt",
    "score": 0.7559969772241748
  },
  {
    "document1": "document0046.txt",
    "document2": "document0050.txt",
    "score": 0.866228464813376
  },
  {
    "document1": "document0047.txt",
    "document2": "document0048.txt",
    "score": 0.833761494802111
  },
  {
    "document1": "document0047.txt",
    "document2": "document0057.txt",
    "score": 0.7189445127600792
  },
  {
    "document1": "document0048.txt",
    "document2": "document0054.txt",
    "score": 0.7412261193222685
  },
  {
    "document1": "document0049.txt",
    "document2": "document0056.txt",
    "score": 0.937039239259924
  },
  {
    "document1": "document0050.txt",
    "document2": "document0056.txt",
    "score": 0.7386704404686705
  },
  {
    "document1": "document0051.txt",
    "document2": "document0053.txt",
    "score": 0.8510139235345476
  },
  {
    "document1": "document0051.txt",
    "document2": "document0054.txt",
    "score": 0.764197221232069
  },
  {
    "document1": "document0051.txt",
    "document2": "document0055.txt",
    "score": 0.7443827635738808
  },
  {
    "document1": "document0053.txt",
    "document2": "document0056.txt",
    "score": 0.7084930184340797
  },
  {
    "document1": "document0054.txt",
    "document2": "document0056.txt",
    "score": 0.8280757680386134
  },
  {
    "document1": "document0054.txt",
    "document2": "document0057.txt",
    "score": 0.7228602579916477
  },
  {
    "document1": "document0056.txt",
    "document2": "document0057.txt",
    "score": 1.0073783986472737
  }
]