[
  {
    "document1": "document0001.txt",
    "document2": "document0003.txt",
    "score": 0.7111394394998154
  },
  {
    "document1": "document0001.txt",
    "document2": "document0006.txt",
    "score": 0.7011913362016499
  },
  {
    "document1": "document0001.txt",
    "document2": "document0007.txt",
    "score": 0.7090043707383454
  },
  {
    "document1": "document0001.txt",
    "document2": "document0013.txt",
    "score": 0.7139102824054471
  },
  {
    "document1": "document0001.txt",
    "document2": "document0019.txt",
    "score": 0.7022923911426643
  },
  {
    "document1": "document0001.txt",
    "document2": "document0021.txt",
    "score": 0.7143270604500822
  },
  {
    "document1": "document0001.txt",
    "document2": "document0023.txt",
    "score": 0.7011884732773264
  },
  {
    "document1": "document0001.txt",
    "document2": "document0029.txt",
    "score": 0.7019780425518032
  },
  {
    "document1": "document0001.txt",
    "document2": "document0035.txt",
    "score": 0.7078401132403509
  },
  {
    "document1": "document0001.txt",
    "document2": "document0037.txt",
    "score": 0.7040178876608755
  },
  {
    "document1": "document0001.txt",
    "document2": "document0038.txt",
    "score": 0.7012228273302855
  },
  {
    "document1": "document0001.txt",
    "document2": "document0041.txt",
    "score": 0.7081397549332951
  },
  {
    "document1": "document0001.txt",
    "document2": "document0046.txt",
    "score": 0.7061120028731862
  },
  {
    "document1": "document0001.txt",
    "document2": "document0048.txt",
    "score": 0.7052075279915869
  },
  {
    "document1": "document0001.txt",
    "document2": "document0057.txt",
    "score": 0.7117526368715155
  },
  {
    "document1": "document0001.txt",
    "document2": "document0060.txt",
    "score": 0.7098480245664812
  },
  {
    "document1": "document0001.txt",
    "document2": "document0062.txt",
    "score": 0.7074576415588882
  },
  {
    "document1": "document0001.txt",
    "document2": "document0067.txt",
    "score": 0.7049342897561384
  },
  {
    "document1": "document0001.txt",
    "document2": "document0073.txt",
    "score": 0.7057375736947503
  },
  {
    "document1": "document0001.txt",
    "document2": "document0074.txt",
    "score": 0.7062055666969675
  },
  {
    "document1": "document0001.txt",
    "document2": "document0075.txt",
    "score": 0.7013239489593139
  },
  {
    "document1": "document0001.txt",
    "document2": "document0082.txt",
    "score": 0.7139629055487713
  },
  {
    "document1": "document0001.txt",
    "document2": "document0084.txt",
    "score": 0.7000879480882102
  },
  {
    "document1": "document0001.txt",
    "document2": "document0092.txt",
    "score": 0.7036533206901557
  },
  {
    "document1": "document0002.txt",
    "document2": "document0009.txt",
    "score": 0.7131570615587993
  },
  {
    "document1": "document0002.txt",
    "document2": "document0028.txt",
    "score": 0.7054130826465261
  },
  {
    "document1": "document0002.txt",
    "document2": "document0058.txt",
    "score": 0.7107501634050096
  },
  {
    "document1": "document0002.txt",
    "document2": "document0059.txt",
    "score": 0.701404485207365
  },
  {
    "document1": "document0002.txt",
    "document2": "document0063.txt",
    "score": 0.7135289245157731
  },
  {
    "document1": "document0002.txt",
    "document2": "document0064.txt",
    "score": 0.7102697709424932
  },
  {
    "document1": "document0002.txt",
    "document2": "document0071.txt",
    "score": 0.7112325004238073
  },
  {
    "document1": "document0002.txt",
    "document2": "document0083.txt",
    "score": 0.7127757871250673
  },
  {
    "document1": "document0002.txt",
    "document2": "document0093.txt",
    "score": 0.7086949119445995
  },
  {
    "document1": "document0003.txt",
    "document2": "document0006.txt",
    "score": 0.70493455799804
  },
  {
    "document1": "document0003.txt",
    "document2": "document0007.txt",
    "score": 0.7128515340217574
  },
  {
    "document1": "document0003.txt",
    "document2": "document0013.txt",
    "score": 0.7122332827766881
  },
  {
    "document1": "document0003.txt",
    "document2": "document0018.txt",
    "score": 0.7011218220143873
  },
  {
    "document1": "document0003.txt",
    "document2": "document0019.txt",
    "score": 0.7060505541046601
  },
  {
    "document1": "document0003.txt",
    "document2": "document0021.txt",
    "score": 0.7104610625897874
  },
  {
    "document1": "document0003.txt",
    "document2": "document0029.txt",
    "score": 0.7057319495159249
  },
  {
    "document1": "document0003.txt",
    "document2": "document0035.txt",
    "score": 0.7116720982837083
  },
  {
    "document1": "document0003.txt",
    "document2": "document0037.txt",
    "score": 0.707799273869959
  },
  {
    "document1": "document0003.txt",
    "document2": "document0038.txt",
    "score": 0.704966477771951
  },
  {
    "document1": "document0003.txt",
    "document2": "document0041.txt",
    "score": 0.7119756568996122
  },
  {
    "document1": "document0003.txt",
    "document2": "document0046.txt",
    "score": 0.7099212562665097
  },
  {
    "document1": "document0003.txt",
    "document2": "document0048.txt",
    "score": 0.7014606429896171
  },
  {
    "document1": "document0003.txt",
    "document2": "document0057.txt",
    "score": 0.7079196119092094
  },
  {
    "document1": "document0003.txt",
    "document2": "document0060.txt",
    "score": 0.7060397271332781
  },
  {
    "document1": "document0003.txt",
    "document2": "document0062.txt",
    "score": 0.7036807740488124
  },
  {
    "document1": "document0003.txt",
    "document2": "document0067.txt",
    "score": 0.7087279139136253
  },
  {
    "document1": "document0003.txt",
    "document2": "document0073.txt",
    "score": 0.7095418701367582
  },
  {
    "document1": "document0003.txt",
    "document2": "document0074.txt",
    "score": 0.7100160569958041
  },
  {
    "document1": "document0003.txt",
    "document2": "document0082.txt",
    "score": 0.7121809578546179
  },
  {
    "document1": "document0003.txt",
    "document2": "document0084.txt",
    "score": 0.7038161023196268
  },
  {
    "document1": "document0004.txt",
    "document2": "document0026.txt",
    "score": 0.7060050514915862
  },
  {
    "document1": "document0004.txt",
    "document2": "document0030.txt",
    "score": 0.7089293399370502
  },
  {
    "document1": "document0004.txt",
    "document2": "document0036.txt",
    "score": 0.7035193730745689
  },
  {
    "document1": "document0004.txt",
    "document2": "document0042.txt",
    "score": 0.700837031070644
  },
  {
    "document1": "document0004.txt",
    "document2": "document0043.txt",
    "score": 0.7112505787656965
  },
  {
    "document1": "document0004.txt",
    "document2": "document0061.txt",
    "score": 0.7105873868950819
  },
  {
    "document1": "document0004.txt",
    "document2": "document0085.txt",
    "score": 0.7016044717938428
  },
  {
    "document1": "document0004.txt",
    "document2": "document0095.txt",
    "score": 0.7081242062011425
  },
  {
    "document1": "document0005.txt",
    "document2": "document0010.txt",
    "score": 0.7147561345744979
  },
  {
    "document1": "document0005.txt",
    "document2": "document0014.txt",
    "score": 0.7103729242186047
  },
  {
    "document1": "document0005.txt",
    "document2": "document0015.txt",
    "score": 0.7089490275786956
  },
  {
    "document1": "document0005.txt",
    "document2": "document0017.txt",
    "score": 0.7079995941738684
  },
  {
    "document1": "document0005.txt",
    "document2": "document0020.txt",
    "score": 0.7025786144885746
  },
  {
    "document1": "document0005.txt",
    "document2": "document0022.txt",
    "score": 0.7142098691061468
  },
  {
    "document1": "document0005.txt",
    "document2": "document0024.txt",
    "score": 0.7132026070992644
  },
  {
    "document1": "document0005.txt",
    "document2": "document0034.txt",
    "score": 0.7068715254108541
  },
  {
    "document1": "document0005.txt",
    "document2": "document0052.txt",
    "score": 0.7032282354416952
  },
  {
    "document1": "document0005.txt",
    "document2": "document0054.txt",
    "score": 0.7084052436045799
  },
  {
    "document1": "document0005.txt",
    "document2": "document0055.txt",
    "score": 0.7104832476872625
  },
  {
    "document1": "document0005.txt",
    "document2": "document0076.txt",
    "score": 0.7060886091994025
  },
  {
    "document1": "document0005.txt",
    "document2": "document0096.txt",
    "score": 0.7098027143380821
  },
  {
    "document1": "document0006.txt",
    "document2": "document0007.txt",
    "score": 0.7070397640622212
  },
  {
    "document1": "document0006.txt",
    "document2": "document0012.txt",
    "score": 0.7061553785741536
  },
  {
    "document1": "document0006.txt",
    "document2": "document0013.txt",
    "score": 0.7022477615607068
  },
  {
    "document1": "document0006.txt",
    "document2": "document0018.txt",
    "score": 0.7110674547079708
  },
  {
    "document1": "document0006.txt",
    "document2": "document0019.txt",
    "score": 0.7138638291365955
  },
  {
    "document1": "document0006.txt",
    "document2": "document0021.txt",
    "score": 0.7005362818827469
  },
  {
    "document1": "document0006.txt",
    "document2": "document0025.txt",
    "score": 0.7002614223527274
  },
  {
    "document1": "document0006.txt",
    "document2": "document0029.txt",
    "score": 0.7141913334748949
  },
  {
    "document1": "document0006.txt",
    "document2": "document0031.txt",
    "score": 0.7051712789858812
  },
  {
    "document1": "document0006.txt",
    "document2": "document0035.txt",
    "score": 0.7082008062317194
  },
  {
    "document1": "document0006.txt",
    "document2": "document0037.txt",
    "score": 0.7120789351544977
  },
  {
    "document1": "document0006.txt",
    "document2": "document0038.txt",
    "score": 0.714981124647737
  },
  {
    "document1": "document0006.txt",
    "document2": "document0041.txt",
    "score": 0.7079011014798712
  },
  {
    "document1": "document0006.txt",
    "document2": "document0046.txt",
    "score": 0.7099414468466796
  },
  {
    "document1": "document0006.txt",
    "document2": "document0067.txt",
    "score": 0.7111397135430466
  },
  {
    "document1": "document0006.txt",
    "document2": "document0069.txt",
    "score": 0.7066518778193619
  },
  {
    "document1": "document0006.txt",
    "document2": "document0073.txt",
    "score": 0.7103213470375312
  },
  {
    "document1": "document0006.txt",
    "document2": "document0074.txt",
    "score": 0.7098466700640554
  },
  {
    "document1": "document0006.txt",
    "document2": "document0081.txt",
    "score": 0.7063952264022252
  },
  {
    "document1": "document0006.txt",
    "document2": "document0082.txt",
    "score": 0.7021972212405327
  },
  {
    "document1": "document0006.txt",
    "document2": "document0084.txt",
    "score": 0.7138567260266411
  },
  {
    "document1": "document0006.txt",
    "document2": "document0086.txt",
    "score": 0.7075247299186823
  },
  {
    "document1": "document0006.txt",
    "document2": "document0087.txt",
    "score": 0.706181250019392
  },
  {
    "document1": "document0006.txt",
    "document2": "document0089.txt",
    "score": 0.7038215139737071
  },
  {
    "document1": "document0006.txt",
    "document2": "document0090.txt",
    "score": 0.7010067584164161
  },
  {
    "document1": "document0006.txt",
    "document2": "document0091.txt",
    "score": 0.7028068452180904
  },
  {
    "document1": "document0007.txt",
    "document2": "document0013.txt",
    "score": 0.7100903701918636
  },
  {
    "document1": "document0007.txt",
    "document2": "document0018.txt",
    "score": 0.7031983939375834
  },
  {
    "document1": "document0007.txt",
    "document2": "document0019.txt",
    "score": 0.708164021791543
  },
  {
    "document1": "document0007.txt",
    "document2": "document0021.txt",
    "score": 0.7083308847986177
  },
  {
    "document1": "document0007.txt",
    "document2": "document0029.txt",
    "score": 0.7078430641796407
  },
  {
    "document1": "document0007.txt",
    "document2": "document0035.txt",
    "score": 0.7138263398178774
  },
  {
    "document1": "document0007.txt",
    "document2": "document0037.txt",
    "score": 0.7099255766983059
  },
  {
    "document1": "document0007.txt",
    "document2": "document0038.txt",
    "score": 0.7070719208941666
  },
  {
    "document1": "document0007.txt",
    "document2": "document0041.txt",
    "score": 0.7141320596263033
  },
  {
    "document1": "document0007.txt",
    "document2": "document0046.txt",
    "score": 0.7120629508878575
  },
  {
    "document1": "document0007.txt",
    "document2": "document0057.txt",
    "score": 0.705807935651709
  },
  {
    "document1": "document0007.txt",
    "document2": "document0060.txt",
    "score": 0.7039419153139482
  },
  {
    "document1": "document0007.txt",
    "document2": "document0062.txt",
    "score": 0.7016005722456992
  },
  {
    "document1": "document0007.txt",
    "document2": "document0067.txt",
    "score": 0.7108609774551862
  },
  {
    "document1": "document0007.txt",
    "document2": "document0073.txt",
    "score": 0.7116808277167808
  },
  {
    "document1": "document0007.txt",
    "document2": "document0074.txt",
    "score": 0.712158434533773
  },
  {
    "document1": "document0007.txt",
    "document2": "document0082.txt",
    "score": 0.7100384192844036
  },
  {
    "document1": "document0007.txt",
    "document2": "document0084.txt",
    "score": 0.7059129738869938
  },
  {
    "document1": "document0008.txt",
    "document2": "document0039.txt",
    "score": 0.7093002900724575
  },
  {
    "document1": "document0008.txt",
    "document2": "document0088.txt",
    "score": 0.7140454608071438
  },
  {
    "document1": "document0009.txt",
    "document2": "document0028.txt",
    "score": 0.7072220692377982
  },
  {
    "document1": "document0009.txt",
    "document2": "document0058.txt",
    "score": 0.7125925484775345
  },
  {
    "document1": "document0009.txt",
    "document2": "document0063.txt",
    "score": 0.7116808277167809
  },
  {
    "document1": "document0009.txt",
    "document2": "document0064.txt",
    "score": 0.7084416982314701
  },
  {
    "document1": "document0009.txt",
    "document2": "document0071.txt",
    "score": 0.7130778499317332
  },
  {
    "document1": "document0009.txt",
    "document2": "document0083.txt",
    "score": 0.7109322816939552
  },
  {
    "document1": "document0009.txt",
    "document2": "document0093.txt",
    "score": 0.7105245645781699
  },
  {
    "document1": "document0010.txt",
    "document2": "document0014.txt",
    "score": 0.710627233773801
  },
  {
    "document1": "document0010.txt",
    "document2": "document0015.txt",
    "score": 0.7086961623428747
  },
  {
    "document1": "document0010.txt",
    "document2": "document0017.txt",
    "score": 0.7082518550606657
  },
  {
    "document1": "document0010.txt",
    "document2": "document0020.txt",
    "score": 0.7028260863442554
  },
  {
    "document1": "document0010.txt",
    "document2": "document0022.txt",
    "score": 0.7139525262137667
  },
  {
    "document1": "document0010.txt",
    "document2": "document0024.txt",
    "score": 0.7129461100917808
  },
  {
    "document1": "document0010.txt",
    "document2": "document0034.txt",
    "score": 0.7071228022059792
  },
  {
    "document1": "document0010.txt",
    "document2": "document0052.txt",
    "score": 0.7034762891123034
  },
  {
    "document1": "document0010.txt",
    "document2": "document0054.txt",
    "score": 0.7086578567453788
  },
  {
    "document1": "document0010.txt",
    "document2": "document0055.txt",
    "score": 0.7107376517516335
  },
  {
    "document1": "document0010.txt",
    "document2": "document0076.txt",
    "score": 0.7063391991216011
  },
  {
    "document1": "document0010.txt",
    "document2": "document0096.txt",
    "score": 0.7095491125410782
  },
  {
    "document1": "document0011.txt",
    "document2": "document0039.txt",
    "score": 0.7012858038729135
  },
  {
    "document1": "document0011.txt",
    "document2": "document0077.txt",
    "score": 0.7017111815909866
  },
  {
    "document1": "document0012.txt",
    "document2": "document0018.txt",
    "score": 0.7100369236098333
  },
  {
    "document1": "document0012.txt",
    "document2": "document0019.txt",
    "score": 0.705038970296632
  },
  {
    "document1": "document0012.txt",
    "document2": "document0020.txt",
    "score": 0.7003386338649078
  },
  {
    "document1": "document0012.txt",
    "document2": "document0025.txt",
    "score": 0.7089384825252563
  },
  {
    "document1": "document0012.txt",
    "document2": "document0029.txt",
    "score": 0.7053567961095741
  },
  {
    "document1": "document0012.txt",
    "document2": "document0031.txt",
    "score": 0.7140001692825548
  },
  {
    "document1": "document0012.txt",
    "document2": "document0037.txt",
    "score": 0.7033071532034805
  },
  {
    "document1": "document0012.txt",
    "document2": "document0038.txt",
    "score": 0.7061233245796094
  },
  {
    "document1": "document0012.txt",
    "document2": "document0040.txt",
    "score": 0.7058762599297841
  },
  {
    "document1": "document0012.txt",
    "document2": "document0044.txt",
    "score": 0.7062997516054529
  },
  {
    "document1": "document0012.txt",
    "document2": "document0046.txt",
    "score": 0.7012339519460512
  },
  {
    "document1": "document0012.txt",
    "document2": "document0067.txt",
    "score": 0.7023960828195285
  },
  {
    "document1": "document0012.txt",
    "document2": "document0069.txt",
    "score": 0.7145034876977522
  },
  {
    "document1": "document0012.txt",
    "document2": "document0073.txt",
    "score": 0.7016023689483631
  },
  {
    "document1": "document0012.txt",
    "document2": "document0074.txt",
    "score": 0.701142043811313
  },
  {
    "document1": "document0012.txt",
    "document2": "document0081.txt",
    "score": 0.7147672436695508
  },
  {
    "document1": "document0012.txt",
    "document2": "document0084.txt",
    "score": 0.7072831256543562
  },
  {
    "document1": "document0012.txt",
    "document2": "document0086.txt",
    "score": 0.7136099187229274
  },
  {
    "document1": "document0012.txt",
    "document2": "document0087.txt",
    "score": 0.7149874967858096
  },
  {
    "document1": "document0012.txt",
    "document2": "document0089.txt",
    "score": 0.7126091197378097
  },
  {
    "document1": "document0012.txt",
    "document2": "document0090.txt",
    "score": 0.7097071592489799
  },
  {
    "document1": "document0012.txt",
    "document2": "document0091.txt",
    "score": 0.7115631875463139
  },
  {
    "document1": "document0012.txt",
    "document2": "document0097.txt",
    "score": 0.704709823579934
  },
  {
    "document1": "document0012.txt",
    "document2": "document0099.txt",
    "score": 0.7077088139834294
  },
  {
    "document1": "document0012.txt",
    "document2": "document0100.txt",
    "score": 0.703647098387899
  },
  {
    "document1": "document0013.txt",
    "document2": "document0019.txt",
    "score": 0.7033530655172123
  },
  {
    "document1": "document0013.txt",
    "document2": "document0021.txt",
    "score": 0.7132256539211763
  },
  {
    "document1": "document0013.txt",
    "document2": "document0023.txt",
    "score": 0.7001361445103608
  },
  {
    "document1": "document0013.txt",
    "document2": "document0029.txt",
    "score": 0.7030375065226702
  },
  {
    "document1": "document0013.txt",
    "document2": "document0035.txt",
    "score": 0.708921791828809
  },
  {
    "document1": "document0013.txt",
    "document2": "document0037.txt",
    "score": 0.7050851677123523
  },
  {
    "document1": "document0013.txt",
    "document2": "document0038.txt",
    "score": 0.7022793745793481
  },
  {
    "document1": "document0013.txt",
    "document2": "document0041.txt",
    "score": 0.7092225484940664
  },
  {
    "document1": "document0013.txt",
    "document2": "document0046.txt",
    "score": 0.7071872118240521
  },
  {
    "document1": "document0013.txt",
    "document2": "document0048.txt",
    "score": 0.7041397837542414
  },
  {
    "document1": "document0013.txt",
    "document2": "document0057.txt",
    "score": 0.710660543906174
  },
  {
    "document1": "document0013.txt",
    "document2": "document0060.txt",
    "score": 0.7087629186874677
  },
  {
    "document1": "document0013.txt",
    "document2": "document0062.txt",
    "score": 0.7063814195830339
  },
  {
    "document1": "document0013.txt",
    "document2": "document0067.txt",
    "score": 0.7060050514915862
  },
  {
    "document1": "document0013.txt",
    "document2": "document0073.txt",
    "score": 0.7068113720839064
  },
  {
    "document1": "document0013.txt",
    "document2": "document0074.txt",
    "score": 0.7072811276373936
  },
  {
    "document1": "document0013.txt",
    "document2": "document0075.txt",
    "score": 0.7002710949364355
  },
  {
    "document1": "document0013.txt",
    "document2": "document0082.txt",
    "score": 0.7149613461712551
  },
  {
    "document1": "document0013.txt",
    "document2": "document0084.txt",
    "score": 0.7011400891697146
  },
  {
    "document1": "document0013.txt",
    "document2": "document0092.txt",
    "score": 0.7025914966002553
  },
  {
    "document1": "document0014.txt",
    "document2": "document0015.txt",
    "score": 0.7044016650245454
  },
  {
    "document1": "document0014.txt",
    "document2": "document0017.txt",
    "score": 0.7126039300116873
  },
  {
    "document1": "document0014.txt",
    "document2": "document0020.txt",
    "score": 0.7070966334279378
  },
  {
    "document1": "document0014.txt",
    "document2": "document0022.txt",
    "score": 0.7095808931134274
  },
  {
    "document1": "document0014.txt",
    "document2": "document0024.txt",
    "score": 0.7085890573356075
  },
  {
    "document1": "document0014.txt",
    "document2": "document0034.txt",
    "score": 0.711458133503513
  },
  {
    "document1": "document0014.txt",
    "document2": "document0040.txt",
    "score": 0.7015349300019371
  },
  {
    "document1": "document0014.txt",
    "document2": "document0044.txt",
    "score": 0.7011186168515183
  },
  {
    "document1": "document0014.txt",
    "document2": "document0052.txt",
    "score": 0.7077567469331555
  },
  {
    "document1": "document0014.txt",
    "document2": "document0054.txt",
    "score": 0.7130159238289449
  },
  {
    "document1": "document0014.txt",
    "document2": "document0055.txt",
    "score": 0.7149021647337142
  },
  {
    "document1": "document0014.txt",
    "document2": "document0076.txt",
    "score": 0.7106628407890065
  },
  {
    "document1": "document0014.txt",
    "document2": "document0096.txt",
    "score": 0.7052419339969808
  },
  {
    "document1": "document0014.txt",
    "document2": "document0097.txt",
    "score": 0.7026881166951654
  },
  {
    "document1": "document0014.txt",
    "document2": "document0100.txt",
    "score": 0.703747181675746
  },
  {
    "document1": "document0015.txt",
    "document2": "document0016.txt",
    "score": 0.7049467534975211
  },
  {
    "document1": "document0015.txt",
    "document2": "document0017.txt",
    "score": 0.7020773311620484
  },
  {
    "document1": "document0015.txt",
    "document2": "document0022.txt",
    "score": 0.7097393590163279
  },
  {
    "document1": "document0015.txt",
    "document2": "document0024.txt",
    "score": 0.7107350826764637
  },
  {
    "document1": "document0015.txt",
    "document2": "document0034.txt",
    "score": 0.7009727837724036
  },
  {
    "document1": "document0015.txt",
    "document2": "document0049.txt",
    "score": 0.7043107126218028
  },
  {
    "document1": "document0015.txt",
    "document2": "document0054.txt",
    "score": 0.7024745589361765
  },
  {
    "document1": "document0015.txt",
    "document2": "document0055.txt",
    "score": 0.7045097272069438
  },
  {
    "document1": "document0015.txt",
    "document2": "document0056.txt",
    "score": 0.7035828356803122
  },
  {
    "document1": "document0015.txt",
    "document2": "document0066.txt",
    "score": 0.7048761215823428
  },
  {
    "document1": "document0015.txt",
    "document2": "document0068.txt",
    "score": 0.7023978274270611
  },
  {
    "document1": "document0015.txt",
    "document2": "document0076.txt",
    "score": 0.7002062796052989
  },
  {
    "document1": "document0015.txt",
    "document2": "document0096.txt",
    "score": 0.7141455797432318
  },
  {
    "document1": "document0016.txt",
    "document2": "document0024.txt",
    "score": 0.700812884863817
  },
  {
    "document1": "document0016.txt",
    "document2": "document0049.txt",
    "score": 0.7143560105318029
  },
  {
    "document1": "document0016.txt",
    "document2": "document0051.txt",
    "score": 0.7013904322523731
  },
  {
    "document1": "document0016.txt",
    "document2": "document0056.txt",
    "score": 0.7136027365448201
  },
  {
    "document1": "document0016.txt",
    "document2": "document0065.txt",
    "score": 0.7069229666036806
  },
  {
    "document1": "document0016.txt",
    "document2": "document0066.txt",
    "score": 0.7149410675150263
  },
  {
    "document1": "document0016.txt",
    "document2": "document0068.txt",
    "score": 0.7123761336558384
  },
  {
    "document1": "document0016.txt",
    "document2": "document0070.txt",
    "score": 0.70347857084258
  },
  {
    "document1": "document0016.txt",
    "document2": "document0096.txt",
    "score": 0.7041073653361982
  },
  {
    "document1": "document0017.txt",
    "document2": "document0020.txt",
    "score": 0.7094626043803087
  },
  {
    "document1": "document0017.txt",
    "document2": "document0022.txt",
    "score": 0.7072139636372129
  },
  {
    "document1": "document0017.txt",
    "document2": "document0024.txt",
    "score": 0.7062301858644696
  },
  {
    "document1": "document0017.txt",
    "document2": "document0025.txt",
    "score": 0.7008469752009229
  },
  {
    "document1": "document0017.txt",
    "document2": "document0034.txt",
    "score": 0.7138592728995653
  },
  {
    "document1": "document0017.txt",
    "document2": "document0040.txt",
    "score": 0.7038546913293333
  },
  {
    "document1": "document0017.txt",
    "document2": "document0044.txt",
    "score": 0.7034348590342244
  },
  {
    "document1": "document0017.txt",
    "document2": "document0052.txt",
    "score": 0.7101281017656838
  },
  {
    "document1": "document0017.txt",
    "document2": "document0054.txt",
    "score": 0.7145994620955728
  },
  {
    "document1": "document0017.txt",
    "document2": "document0055.txt",
    "score": 0.7124928232868882
  },
  {
    "document1": "document0017.txt",
    "document2": "document0076.txt",
    "score": 0.7130576388177453
  },
  {
    "document1": "document0017.txt",
    "document2": "document0090.txt",
    "score": 0.7001020786281195
  },
  {
    "document1": "document0017.txt",
    "document2": "document0096.txt",
    "score": 0.7029106030483959
  },
  {
    "document1": "document0017.txt",
    "document2": "document0097.txt",
    "score": 0.705017582671078
  },
  {
    "document1": "document0017.txt",
    "document2": "document0099.txt",
    "score": 0.7020469737811597
  },
  {
    "document1": "document0017.txt",
    "document2": "document0100.txt",
    "score": 0.7060855037627517
  },
  {
    "document1": "document0018.txt",
    "document2": "document0019.txt",
    "score": 0.7099320156600086
  },
  {
    "document1": "document0018.txt",
    "document2": "document0025.txt",
    "score": 0.7040621936319315
  },
  {
    "document1": "document0018.txt",
    "document2": "document0029.txt",
    "score": 0.710255272450209
  },
  {
    "document1": "document0018.txt",
    "document2": "document0031.txt",
    "score": 0.7090395324374211
  },
  {
    "document1": "document0018.txt",
    "document2": "document0035.txt",
    "score": 0.7043437901353555
  },
  {
    "document1": "document0018.txt",
    "document2": "document0037.txt",
    "score": 0.708170422132637
  },
  {
    "document1": "document0018.txt",
    "document2": "document0038.txt",
    "score": 0.7110348561155793
  },
  {
    "document1": "document0018.txt",
    "document2": "document0040.txt",
    "score": 0.701052221933468
  },
  {
    "document1": "document0018.txt",
    "document2": "document0041.txt",
    "score": 0.7040481141412044
  },
  {
    "document1": "document0018.txt",
    "document2": "document0044.txt",
    "score": 0.7014684335347422
  },
  {
    "document1": "document0018.txt",
    "document2": "document0046.txt",
    "score": 0.7060611707895619
  },
  {
    "document1": "document0018.txt",
    "document2": "document0067.txt",
    "score": 0.707243563430761
  },
  {
    "document1": "document0018.txt",
    "document2": "document0069.txt",
    "score": 0.7105400986842315
  },
  {
    "document1": "document0018.txt",
    "document2": "document0073.txt",
    "score": 0.7064360259896311
  },
  {
    "document1": "document0018.txt",
    "document2": "document0074.txt",
    "score": 0.705967654390667
  },
  {
    "document1": "document0018.txt",
    "document2": "document0081.txt",
    "score": 0.7102799989069885
  },
  {
    "document1": "document0018.txt",
    "document2": "document0084.txt",
    "score": 0.7122142938750249
  },
  {
    "document1": "document0018.txt",
    "document2": "document0086.txt",
    "score": 0.7114246378701884
  },
  {
    "document1": "document0018.txt",
    "document2": "document0087.txt",
    "score": 0.7100631434162206
  },
  {
    "document1": "document0018.txt",
    "document2": "document0089.txt",
    "score": 0.7076714089704373
  },
  {
    "document1": "document0018.txt",
    "document2": "document0090.txt",
    "score": 0.704817897723987
  },
  {
    "document1": "document0018.txt",
    "document2": "document0091.txt",
    "score": 0.7066428426085312
  },
  {
    "document1": "document0018.txt",
    "document2": "document0099.txt",
    "score": 0.7028533977667306
  },
  {
    "document1": "document0019.txt",
    "document2": "document0021.txt",
    "score": 0.7016346895216431
  },
  {
    "document1": "document0019.txt",
    "document2": "document0029.txt",
    "score": 0.7146857700557319
  },
  {
    "document1": "document0019.txt",
    "document2": "document0031.txt",
    "score": 0.7040587500334736
  },
  {
    "document1": "document0019.txt",
    "document2": "document0035.txt",
    "score": 0.7093295761544619
  },
  {
    "document1": "document0019.txt",
    "document2": "document0037.txt",
    "score": 0.713222545763049
  },
  {
    "document1": "document0019.txt",
    "document2": "document0038.txt",
    "score": 0.7138967340022162
  },
  {
    "document1": "document0019.txt",
    "document2": "document0041.txt",
    "score": 0.7090287096763325
  },
  {
    "document1": "document0019.txt",
    "document2": "document0046.txt",
    "score": 0.7110769220319844
  },
  {
    "document1": "document0019.txt",
    "document2": "document0067.txt",
    "score": 0.7122797628741973
  },
  {
    "document1": "document0019.txt",
    "document2": "document0069.txt",
    "score": 0.7055335207056553
  },
  {
    "document1": "document0019.txt",
    "document2": "document0073.txt",
    "score": 0.7114582761223172
  },
  {
    "document1": "document0019.txt",
    "document2": "document0074.txt",
    "score": 0.7109817819984391
  },
  {
    "document1": "document0019.txt",
    "document2": "document0081.txt",
    "score": 0.7052778759826028
  },
  {
    "document1": "document0019.txt",
    "document2": "document0082.txt",
    "score": 0.7033023224950288
  },
  {
    "document1": "document0019.txt",
    "document2": "document0084.txt",
    "score": 0.7127107317546102
  },
  {
    "document1": "document0019.txt",
    "document2": "document0086.txt",
    "score": 0.7064029603951097
  },
  {
    "document1": "document0019.txt",
    "document2": "document0087.txt",
    "score": 0.7050647400535934
  },
  {
    "document1": "document0019.txt",
    "document2": "document0089.txt",
    "score": 0.7027143414416516
  },
  {
    "document1": "document0019.txt",
    "document2": "document0091.txt",
    "score": 0.7017037262613329
  },
  {
    "document1": "document0020.txt",
    "document2": "document0022.txt",
    "score": 0.7018079427127283
  },
  {
    "document1": "document0020.txt",
    "document2": "document0024.txt",
    "score": 0.7008429900588239
  },
  {
    "document1": "document0020.txt",
    "document2": "document0025.txt",
    "score": 0.7062342489693989
  },
  {
    "document1": "document0020.txt",
    "document2": "document0031.txt",
    "score": 0.7013057019395257
  },
  {
    "document1": "document0020.txt",
    "document2": "document0034.txt",
    "score": 0.7106007493718908
  },
  {
    "document1": "document0020.txt",
    "document2": "document0040.txt",
    "score": 0.7093002900724575
  },
  {
    "document1": "document0020.txt",
    "document2": "document0044.txt",
    "score": 0.7088723787118724
  },
  {
    "document1": "document0020.txt",
    "document2": "document0052.txt",
    "score": 0.7143378038499278
  },
  {
    "document1": "document0020.txt",
    "document2": "document0054.txt",
    "score": 0.7090554840932766
  },
  {
    "document1": "document0020.txt",
    "document2": "document0055.txt",
    "score": 0.7069875821118389
  },
  {
    "document1": "document0020.txt",
    "document2": "document0076.txt",
    "score": 0.7113958763945522
  },
  {
    "document1": "document0020.txt",
    "document2": "document0081.txt",
    "score": 0.700103965517334
  },
  {
    "document1": "document0020.txt",
    "document2": "document0087.txt",
    "score": 0.7003133017852082
  },
  {
    "document1": "document0020.txt",
    "document2": "document0089.txt",
    "score": 0.7026432466934139
  },
  {
    "document1": "document0020.txt",
    "document2": "document0090.txt",
    "score": 0.7054747485009937
  },
  {
    "document1": "document0020.txt",
    "document2": "document0091.txt",
    "score": 0.7036573158775417
  },
  {
    "document1": "document0020.txt",
    "document2": "document0097.txt",
    "score": 0.710485453257744
  },
  {
    "document1": "document0020.txt",
    "document2": "document0099.txt",
    "score": 0.7074576415588882
  },
  {
    "document1": "document0020.txt",
    "document2": "document0100.txt",
    "score": 0.7115736889529792
  },
  {
    "document1": "document0021.txt",
    "document2": "document0023.txt",
    "score": 0.701845101407027
  },
  {
    "document1": "document0021.txt",
    "document2": "document0029.txt",
    "score": 0.7013210950865837
  },
  {
    "document1": "document0021.txt",
    "document2": "document0033.txt",
    "score": 0.7002286636455118
  },
  {
    "document1": "document0021.txt",
    "document2": "document0035.txt",
    "score": 0.7071693210960422
  },
  {
    "document1": "document0021.txt",
    "document2": "document0037.txt",
    "score": 0.7033560699087368
  },
  {
    "document1": "document0021.txt",
    "document2": "document0038.txt",
    "score": 0.7005676970728597
  },
  {
    "document1": "document0021.txt",
    "document2": "document0041.txt",
    "score": 0.7074682677021219
  },
  {
    "document1": "document0021.txt",
    "document2": "document0046.txt",
    "score": 0.7054452435701665
  },
  {
    "document1": "document0021.txt",
    "document2": "document0048.txt",
    "score": 0.705873728032547
  },
  {
    "document1": "document0021.txt",
    "document2": "document0057.txt",
    "score": 0.712433948016505
  },
  {
    "document1": "document0021.txt",
    "document2": "document0060.txt",
    "score": 0.7105250004725314
  },
  {
    "document1": "document0021.txt",
    "document2": "document0062.txt",
    "score": 0.7081291041043031
  },
  {
    "document1": "document0021.txt",
    "document2": "document0067.txt",
    "score": 0.704270302226239
  },
  {
    "document1": "document0021.txt",
    "document2": "document0073.txt",
    "score": 0.7050716935731557
  },
  {
    "document1": "document0021.txt",
    "document2": "document0074.txt",
    "score": 0.705538587999267
  },
  {
    "document1": "document0021.txt",
    "document2": "document0075.txt",
    "score": 0.7019809032936872
  },
  {
    "document1": "document0021.txt",
    "document2": "document0082.txt",
    "score": 0.7132781593941492
  },
  {
    "document1": "document0021.txt",
    "document2": "document0092.txt",
    "score": 0.7043158451645131
  },
  {
    "document1": "document0021.txt",
    "document2": "document0098.txt",
    "score": 0.7006305040655951
  },
  {
    "document1": "document0022.txt",
    "document2": "document0024.txt",
    "score": 0.7140042522795069
  },
  {
    "document1": "document0022.txt",
    "document2": "document0034.txt",
    "score": 0.7060889691103092
  },
  {
    "document1": "document0022.txt",
    "document2": "document0052.txt",
    "score": 0.702455746582229
  },
  {
    "document1": "document0022.txt",
    "document2": "document0054.txt",
    "score": 0.7076185126003626
  },
  {
    "document1": "document0022.txt",
    "document2": "document0055.txt",
    "score": 0.7096909212887489
  },
  {
    "document1": "document0022.txt",
    "document2": "document0076.txt",
    "score": 0.7053081985242152
  },
  {
    "document1": "document0022.txt",
    "document2": "document0096.txt",
    "score": 0.7105953405615002
  },
  {
    "document1": "document0023.txt",
    "document2": "document0027.txt",
    "score": 0.7013806528865922
  },
  {
    "document1": "document0023.txt",
    "document2": "document0032.txt",
    "score": 0.7095677605258855
  },
  {
    "document1": "document0023.txt",
    "document2": "document0033.txt",
    "score": 0.7133225007542897
  },
  {
    "document1": "document0023.txt",
    "document2": "document0045.txt",
    "score": 0.7104204880991094
  },
  {
    "document1": "document0023.txt",
    "document2": "document0048.txt",
    "score": 0.710857869333553
  },
  {
    "document1": "document0023.txt",
    "document2": "document0057.txt",
    "score": 0.7043326982048649
  },
  {
    "document1": "document0023.txt",
    "document2": "document0060.txt",
    "score": 0.7062013141732799
  },
  {
    "document1": "document0023.txt",
    "document2": "document0062.txt",
    "score": 0.7085813209186091
  },
  {
    "document1": "document0023.txt",
    "document2": "document0072.txt",
    "score": 0.7075906376383231
  },
  {
    "document1": "document0023.txt",
    "document2": "document0075.txt",
    "score": 0.7148721281028624
  },
  {
    "document1": "document0023.txt",
    "document2": "document0079.txt",
    "score": 0.7089293399370502
  },
  {
    "document1": "document0023.txt",
    "document2": "document0080.txt",
    "score": 0.703668430529705
  },
  {
    "document1": "document0023.txt",
    "document2": "document0082.txt",
    "score": 0.7001863034302798
  },
  {
    "document1": "document0023.txt",
    "document2": "document0092.txt",
    "score": 0.712451277943437
  },
  {
    "document1": "document0023.txt",
    "document2": "document0094.txt",
    "score": 0.7106253525762304
  },
  {
    "document1": "document0023.txt",
    "document2": "document0098.txt",
    "score": 0.7137431090327466
  },
  {
    "document1": "document0024.txt",
    "document2": "document0034.txt",
    "score": 0.7051090609719183
  },
  {
    "document1": "document0024.txt",
    "document2": "document0049.txt",
    "score": 0.7001863034302798
  },
  {
    "document1": "document0024.txt",
    "document2": "document0052.txt",
    "score": 0.7014885077015625
  },
  {
    "document1": "document0024.txt",
    "document2": "document0054.txt",
    "score": 0.7066333495299687
  },
  {
    "document1": "document0024.txt",
    "document2": "document0055.txt",
    "score": 0.7086987137036087
  },
  {
    "document1": "document0024.txt",
    "document2": "document0066.txt",
    "score": 0.7007433017706334
  },
  {
    "document1": "document0024.txt",
    "document2": "document0076.txt",
    "score": 0.7043309908960829
  },
  {
    "document1": "document0024.txt",
    "document2": "document0096.txt",
    "score": 0.7115939394810554
  },
  {
    "document1": "document0025.txt",
    "document2": "document0031.txt",
    "score": 0.7099355304107363
  },
  {
    "document1": "document0025.txt",
    "document2": "document0034.txt",
    "score": 0.7019510122693364
  },
  {
    "document1": "document0025.txt",
    "document2": "document0038.txt",
    "score": 0.700230042757775
  },
  {
    "document1": "document0025.txt",
    "document2": "document0040.txt",
    "score": 0.7118888977996946
  },
  {
    "document1": "document0025.txt",
    "document2": "document0044.txt",
    "score": 0.7123211783307091
  },
  {
    "document1": "document0025.txt",
    "document2": "document0052.txt",
    "score": 0.7055776324176285
  },
  {
    "document1": "document0025.txt",
    "document2": "document0054.txt",
    "score": 0.7004521086792251
  },
  {
    "document1": "document0025.txt",
    "document2": "document0069.txt",
    "score": 0.7084380384281844
  },
  {
    "document1": "document0025.txt",
    "document2": "document0076.txt",
    "score": 0.7027224415376864
  },
  {
    "document1": "document0025.txt",
    "document2": "document0081.txt",
    "score": 0.7086965132429305
  },
  {
    "document1": "document0025.txt",
    "document2": "document0084.txt",
    "score": 0.7013655185653886
  },
  {
    "document1": "document0025.txt",
    "document2": "document0086.txt",
    "score": 0.7075624246919848
  },
  {
    "document1": "document0025.txt",
    "document2": "document0087.txt",
    "score": 0.7089123628099016
  },
  {
    "document1": "document0025.txt",
    "document2": "document0089.txt",
    "score": 0.7113142538617292
  },
  {
    "document1": "document0025.txt",
    "document2": "document0090.txt",
    "score": 0.7142318212607729
  },
  {
    "document1": "document0025.txt",
    "document2": "document0091.txt",
    "score": 0.7123593201107982
  },
  {
    "document1": "document0025.txt",
    "document2": "document0097.txt",
    "score": 0.7106981350818243
  },
  {
    "document1": "document0025.txt",
    "document2": "document0099.txt",
    "score": 0.7137593167985491
  },
  {
    "document1": "document0025.txt",
    "document2": "document0100.txt",
    "score": 0.7096130953149671
  },
  {
    "document1": "document0026.txt",
    "document2": "document0030.txt",
    "score": 0.7120296029484288
  },
  {
    "document1": "document0026.txt",
    "document2": "document0042.txt",
    "score": 0.7096842961998685
  },
  {
    "document1": "document0026.txt",
    "document2": "document0043.txt",
    "score": 0.702355237934622
  },
  {
    "document1": "document0026.txt",
    "document2": "document0051.txt",
    "score": 0.7060246878966165
  },
  {
    "document1": "document0026.txt",
    "document2": "document0053.txt",
    "score": 0.7080060216239761
  },
  {
    "document1": "document0026.txt",
    "document2": "document0061.txt",
    "score": 0.7103635028043858
  },
  {
    "document1": "document0026.txt",
    "document2": "document0065.txt",
    "score": 0.700509794002707
  },
  {
    "document1": "document0026.txt",
    "document2": "document0070.txt",
    "score": 0.7039174433879688
  },
  {
    "document1": "document0026.txt",
    "document2": "document0085.txt",
    "score": 0.7104760938501937
  },
  {
    "document1": "document0026.txt",
    "document2": "document0095.txt",
    "score": 0.7128454145321336
  },
  {
    "document1": "document0027.txt",
    "document2": "document0028.txt",
    "score": 0.706627896228657
  },
  {
    "document1": "document0027.txt",
    "document2": "document0032.txt",
    "score": 0.7066742003388303
  },
  {
    "document1": "document0027.txt",
    "document2": "document0033.txt",
    "score": 0.7030039420123599
  },
  {
    "document1": "document0027.txt",
    "document2": "document0045.txt",
    "score": 0.7058323921836408
  },
  {
    "document1": "document0027.txt",
    "document2": "document0058.txt",
    "score": 0.7013668564548712
  },
  {
    "document1": "document0027.txt",
    "document2": "document0071.txt",
    "score": 0.7009009376708482
  },
  {
    "document1": "document0027.txt",
    "document2": "document0072.txt",
    "score": 0.7086450693043489
  },
  {
    "document1": "document0027.txt",
    "document2": "document0075.txt",
    "score": 0.7012451490019617
  },
  {
    "document1": "document0027.txt",
    "document2": "document0079.txt",
    "score": 0.7073076744760745
  },
  {
    "document1": "document0027.txt",
    "document2": "document0080.txt",
    "score": 0.7126355696440487
  },
  {
    "document1": "document0027.txt",
    "document2": "document0093.txt",
    "score": 0.7033696816641462
  },
  {
    "document1": "document0027.txt",
    "document2": "document0094.txt",
    "score": 0.7056308815981749
  },
  {
    "document1": "document0027.txt",
    "document2": "document0098.txt",
    "score": 0.7025985976385832
  },
  {
    "document1": "document0028.txt",
    "document2": "document0058.txt",
    "score": 0.7096003325241709
  },
  {
    "document1": "document0028.txt",
    "document2": "document0063.txt",
    "score": 0.7039754652335037
  },
  {
    "document1": "document0028.txt",
    "document2": "document0064.txt",
    "score": 0.7008222311400423
  },
  {
    "document1": "document0028.txt",
    "document2": "document0071.txt",
    "score": 0.7091206459420353
  },
  {
    "document1": "document0028.txt",
    "document2": "document0072.txt",
    "score": 0.7004390475148063
  },
  {
    "document1": "document0028.txt",
    "document2": "document0080.txt",
    "score": 0.7043158451645131
  },
  {
    "document1": "document0028.txt",
    "document2": "document0083.txt",
    "score": 0.7032466278020948
  },
  {
    "document1": "document0028.txt",
    "document2": "document0093.txt",
    "score": 0.7116619028930038
  },
  {
    "document1": "document0029.txt",
    "document2": "document0031.txt",
    "score": 0.7043754689159544
  },
  {
    "document1": "document0029.txt",
    "document2": "document0035.txt",
    "score": 0.7090073335040874
  },
  {
    "document1": "document0029.txt",
    "document2": "document0037.txt",
    "score": 0.7128960771010814
  },
  {
    "document1": "document0029.txt",
    "document2": "document0038.txt",
    "score": 0.7142242734416264
  },
  {
    "document1": "document0029.txt",
    "document2": "document0041.txt",
    "score": 0.7087067978701772
  },
  {
    "document1": "document0029.txt",
    "document2": "document0046.txt",
    "score": 0.710752769903425
  },
  {
    "document1": "document0029.txt",
    "document2": "document0067.txt",
    "score": 0.7119543082437753
  },
  {
    "document1": "document0029.txt",
    "document2": "document0069.txt",
    "score": 0.7058519026195841
  },
  {
    "document1": "document0029.txt",
    "document2": "document0073.txt",
    "score": 0.7111337099832971
  },
  {
    "document1": "document0029.txt",
    "document2": "document0074.txt",
    "score": 0.7106577333099033
  },
  {
    "document1": "document0029.txt",
    "document2": "document0081.txt",
    "score": 0.7055959706345466
  },
  {
    "document1": "document0029.txt",
    "document2": "document0082.txt",
    "score": 0.7029868212423361
  },
  {
    "document1": "document0029.txt",
    "document2": "document0084.txt",
    "score": 0.7130370013288077
  },
  {
    "document1": "document0029.txt",
    "document2": "document0086.txt",
    "score": 0.7067223160709182
  },
  {
    "document1": "document0029.txt",
    "document2": "document0087.txt",
    "score": 0.7053825948830137
  },
  {
    "document1": "document0029.txt",
    "document2": "document0089.txt",
    "score": 0.7030295319953537
  },
  {
    "document1": "document0029.txt",
    "document2": "document0090.txt",
    "score": 0.7002228534671212
  },
  {
    "document1": "document0029.txt",
    "document2": "document0091.txt",
    "score": 0.7020177602809029
  },
  {
    "document1": "document0030.txt",
    "document2": "document0042.txt",
    "score": 0.7067524101757141
  },
  {
    "document1": "document0030.txt",
    "document2": "document0043.txt",
    "score": 0.7052419339969808
  },
  {
    "document1": "document0030.txt",
    "document2": "document0051.txt",
    "score": 0.703129945172409
  },
  {
    "document1": "document0030.txt",
    "document2": "document0053.txt",
    "score": 0.7050910711161218
  },
  {
    "document1": "document0030.txt",
    "document2": "document0061.txt",
    "score": 0.7133316116806186
  },
  {
    "document1": "document0030.txt",
    "document2": "document0070.txt",
    "score": 0.7010444439553304
  },
  {
    "document1": "document0030.txt",
    "document2": "document0085.txt",
    "score": 0.7075362760581294
  },
  {
    "document1": "document0030.txt",
    "document2": "document0095.txt",
    "score": 0.7141925357035027
  },
  {
    "document1": "document0031.txt",
    "document2": "document0037.txt",
    "score": 0.702332999874398
  },
  {
    "document1": "document0031.txt",
    "document2": "document0038.txt",
    "score": 0.7051393360248916
  },
  {
    "document1": "document0031.txt",
    "document2": "document0040.txt",
    "score": 0.7068628047442814
  },
  {
    "document1": "document0031.txt",
    "document2": "document0044.txt",
    "score": 0.707287760428725
  },
  {
    "document1": "document0031.txt",
    "document2": "document0046.txt",
    "score": 0.7002671393268204
  },
  {
    "document1": "document0031.txt",
    "document2": "document0052.txt",
    "score": 0.7006606177621615
  },
  {
    "document1": "document0031.txt",
    "document2": "document0067.txt",
    "score": 0.7014251449840617
  },
  {
    "document1": "document0031.txt",
    "document2": "document0069.txt",
    "score": 0.7134911860521983
  },
  {
    "document1": "document0031.txt",
    "document2": "document0073.txt",
    "score": 0.7006342457002713
  },
  {
    "document1": "document0031.txt",
    "document2": "document0074.txt",
    "score": 0.7001755585641726
  },
  {
    "document1": "document0031.txt",
    "document2": "document0081.txt",
    "score": 0.7137540746339345
  },
  {
    "document1": "document0031.txt",
    "document2": "document0084.txt",
    "score": 0.7062951327785782
  },
  {
    "document1": "document0031.txt",
    "document2": "document0086.txt",
    "score": 0.7126005666062212
  },
  {
    "document1": "document0031.txt",
    "document2": "document0087.txt",
    "score": 0.7139736045539231
  },
  {
    "document1": "document0031.txt",
    "document2": "document0089.txt",
    "score": 0.7136185002608889
  },
  {
    "document1": "document0031.txt",
    "document2": "document0090.txt",
    "score": 0.7107068131402444
  },
  {
    "document1": "document0031.txt",
    "document2": "document0091.txt",
    "score": 0.7125690828442169
  },
  {
    "document1": "document0031.txt",
    "document2": "document0097.txt",
    "score": 0.7056923171408856
  },
  {
    "document1": "document0031.txt",
    "document2": "document0099.txt",
    "score": 0.7087016674664586
  },
  {
    "document1": "document0031.txt",
    "document2": "document0100.txt",
    "score": 0.7046258769075838
  },
  {
    "document1": "document0032.txt",
    "document2": "document0033.txt",
    "score": 0.7112384492301055
  },
  {
    "document1": "document0032.txt",
    "document2": "document0045.txt",
    "score": 0.7141483706263325
  },
  {
    "document1": "document0032.txt",
    "document2": "document0048.txt",
    "score": 0.7054867113008603
  },
  {
    "document1": "document0032.txt",
    "document2": "document0060.txt",
    "score": 0.7009166558974568
  },
  {
    "document1": "document0032.txt",
    "document2": "document0062.txt",
    "score": 0.7032521634460197
  },
  {
    "document1": "document0032.txt",
    "document2": "document0072.txt",
    "score": 0.7130008200892615
  },
  {
    "document1": "document0032.txt",
    "document2": "document0075.txt",
    "score": 0.7094282789870274
  },
  {
    "document1": "document0032.txt",
    "document2": "document0079.txt",
    "score": 0.7143640870666432
  },
  {
    "document1": "document0032.txt",
    "document2": "document0080.txt",
    "score": 0.7090054550159833
  },
  {
    "document1": "document0032.txt",
    "document2": "document0092.txt",
    "score": 0.7070510553201874
  },
  {
    "document1": "document0032.txt",
    "document2": "document0094.txt",
    "score": 0.713941103124477
  },
  {
    "document1": "document0032.txt",
    "document2": "document0098.txt",
    "score": 0.7108213124942505
  },
  {
    "document1": "document0033.txt",
    "document2": "document0045.txt",
    "score": 0.7120959806246373
  },
  {
    "document1": "document0033.txt",
    "document2": "document0048.txt",
    "score": 0.7091893207338859
  },
  {
    "document1": "document0033.txt",
    "document2": "document0057.txt",
    "score": 0.7027016072494564
  },
  {
    "document1": "document0033.txt",
    "document2": "document0060.txt",
    "score": 0.7045593503063498
  },
  {
    "document1": "document0033.txt",
    "document2": "document0062.txt",
    "score": 0.7069256775469672
  },
  {
    "document1": "document0033.txt",
    "document2": "document0072.txt",
    "score": 0.7092500904453168
  },
  {
    "document1": "document0033.txt",
    "document2": "document0075.txt",
    "score": 0.7131812592521778
  },
  {
    "document1": "document0033.txt",
    "document2": "document0079.txt",
    "score": 0.7105964154238816
  },
  {
    "document1": "document0033.txt",
    "document2": "document0080.txt",
    "score": 0.7053051946166277
  },
  {
    "document1": "document0033.txt",
    "document2": "document0092.txt",
    "score": 0.7107738025276326
  },
  {
    "document1": "document0033.txt",
    "document2": "document0094.txt",
    "score": 0.7123019953895461
  },
  {
    "document1": "document0033.txt",
    "document2": "document0098.txt",
    "score": 0.7145918000566696
  },
  {
    "document1": "document0034.txt",
    "document2": "document0040.txt",
    "score": 0.7049708303128185
  },
  {
    "document1": "document0034.txt",
    "document2": "document0044.txt",
    "score": 0.704549321165237
  },
  {
    "document1": "document0034.txt",
    "document2": "document0052.txt",
    "score": 0.7112688090785734
  },
  {
    "document1": "document0034.txt",
    "document2": "document0054.txt",
    "score": 0.713446138268203
  },
  {
    "document1": "document0034.txt",
    "document2": "document0055.txt",
    "score": 0.7113474486797678
  },
  {
    "document1": "document0034.txt",
    "document2": "document0076.txt",
    "score": 0.7142094991793818
  },
  {
    "document1": "document0034.txt",
    "document2": "document0090.txt",
    "score": 0.7012030868455446
  },
  {
    "document1": "document0034.txt",
    "document2": "document0096.txt",
    "score": 0.7018026982146175
  },
  {
    "document1": "document0034.txt",
    "document2": "document0097.txt",
    "score": 0.7061383451810473
  },
  {
    "document1": "document0034.txt",
    "document2": "document0099.txt",
    "score": 0.7031558638663583
  },
  {
    "document1": "document0034.txt",
    "document2": "document0100.txt",
    "score": 0.7072104846444168
  },
  {
    "document1": "document0035.txt",
    "document2": "document0037.txt",
    "score": 0.7110981392457035
  },
  {
    "document1": "document0035.txt",
    "document2": "document0038.txt",
    "score": 0.7082330925490713
  },
  {
    "document1": "document0035.txt",
    "document2": "document0041.txt",
    "score": 0.7147075536727218
  },
  {
    "document1": "document0035.txt",
    "document2": "document0046.txt",
    "score": 0.7132439144383014
  },
  {
    "document1": "document0035.txt",
    "document2": "document0057.txt",
    "score": 0.7046565589589626
  },
  {
    "document1": "document0035.txt",
    "document2": "document0060.txt",
    "score": 0.7027981693661575
  },
  {
    "document1": "document0035.txt",
    "document2": "document0062.txt",
    "score": 0.7004665149341877
  },
  {
    "document1": "document0035.txt",
    "document2": "document0067.txt",
    "score": 0.7120372305028337
  },
  {
    "document1": "document0035.txt",
    "document2": "document0069.txt",
    "score": 0.7000310188586224
  },
  {
    "document1": "document0035.txt",
    "document2": "document0073.txt",
    "score": 0.7128602976189117
  },
  {
    "document1": "document0035.txt",
    "document2": "document0074.txt",
    "score": 0.7133397707453494
  },
  {
    "document1": "document0035.txt",
    "document2": "document0082.txt",
    "score": 0.7088700469724812
  },
  {
    "document1": "document0035.txt",
    "document2": "document0084.txt",
    "score": 0.7070694631201101
  },
  {
    "document1": "document0035.txt",
    "document2": "document0086.txt",
    "score": 0.7008833449147499
  },
  {
    "document1": "document0036.txt",
    "document2": "document0043.txt",
    "score": 0.707184423700777
  },
  {
    "document1": "document0036.txt",
    "document2": "document0047.txt",
    "score": 0.7070890357842297
  },
  {
    "document1": "document0037.txt",
    "document2": "document0038.txt",
    "score": 0.7121116474201787
  },
  {
    "document1": "document0037.txt",
    "document2": "document0041.txt",
    "score": 0.710795468544811
  },
  {
    "document1": "document0037.txt",
    "document2": "document0046.txt",
    "score": 0.7128558969436547
  },
  {
    "document1": "document0037.txt",
    "document2": "document0057.txt",
    "score": 0.7008772309156245
  },
  {
    "document1": "document0037.txt",
    "document2": "document0067.txt",
    "score": 0.7140658386320606
  },
  {
    "document1": "document0037.txt",
    "document2": "document0069.txt",
    "score": 0.7037986554469108
  },
  {
    "document1": "document0037.txt",
    "document2": "document0073.txt",
    "score": 0.713239508210925
  },
  {
    "document1": "document0037.txt",
    "document2": "document0074.txt",
    "score": 0.7127601929402405
  },
  {
    "document1": "document0037.txt",
    "document2": "document0081.txt",
    "score": 0.7035445853190093
  },
  {
    "document1": "document0037.txt",
    "document2": "document0082.txt",
    "score": 0.7050341095865171
  },
  {
    "document1": "document0037.txt",
    "document2": "document0084.txt",
    "score": 0.7109326124126206
  },
  {
    "document1": "document0037.txt",
    "document2": "document0086.txt",
    "score": 0.7046627572260022
  },
  {
    "document1": "document0037.txt",
    "document2": "document0087.txt",
    "score": 0.7033327639161405
  },
  {
    "document1": "document0037.txt",
    "document2": "document0089.txt",
    "score": 0.7009969667652955
  },
  {
    "document1": "document0038.txt",
    "document2": "document0041.txt",
    "score": 0.7079333544585231
  },
  {
    "document1": "document0038.txt",
    "document2": "document0046.txt",
    "score": 0.7099739256011117
  },
  {
    "document1": "document0038.txt",
    "document2": "document0067.txt",
    "score": 0.7111723235852437
  },
  {
    "document1": "document0038.txt",
    "document2": "document0069.txt",
    "score": 0.7066197680479608
  },
  {
    "document1": "document0038.txt",
    "document2": "document0073.txt",
    "score": 0.7103538675208727
  },
  {
    "document1": "document0038.txt",
    "document2": "document0074.txt",
    "score": 0.7098791383928484
  },
  {
    "document1": "document0038.txt",
    "document2": "document0081.txt",
    "score": 0.7063631454428013
  },
  {
    "document1": "document0038.txt",
    "document2": "document0082.txt",
    "score": 0.7022288284441651
  },
  {
    "document1": "document0038.txt",
    "document2": "document0084.txt",
    "score": 0.7138238254536017
  },
  {
    "document1": "document0038.txt",
    "document2": "document0086.txt",
    "score": 0.7074925224861423
  },
  {
    "document1": "document0038.txt",
    "document2": "document0087.txt",
    "score": 0.706149193114427
  },
  {
    "document1": "document0038.txt",
    "document2": "document0089.txt",
    "score": 0.7037897243341282
  },
  {
    "document1": "document0038.txt",
    "document2": "document0090.txt",
    "score": 0.7009752923028607
  },
  {
    "document1": "document0038.txt",
    "document2": "document0091.txt",
    "score": 0.7027751716154766
  },
  {
    "document1": "document0039.txt",
    "document2": "document0088.txt",
    "score": 0.710253833716819
  },
  {
    "document1": "document0040.txt",
    "document2": "document0044.txt",
    "score": 0.7145780428447934
  },
  {
    "document1": "document0040.txt",
    "document2": "document0052.txt",
    "score": 0.708636663393853
  },
  {
    "document1": "document0040.txt",
    "document2": "document0054.txt",
    "score": 0.7034554780301991
  },
  {
    "document1": "document0040.txt",
    "document2": "document0055.txt",
    "score": 0.7014280235390008
  },
  {
    "document1": "document0040.txt",
    "document2": "document0069.txt",
    "score": 0.7053811109184291
  },
  {
    "document1": "document0040.txt",
    "document2": "document0076.txt",
    "score": 0.7057506703158264
  },
  {
    "document1": "document0040.txt",
    "document2": "document0081.txt",
    "score": 0.7056368489282412
  },
  {
    "document1": "document0040.txt",
    "document2": "document0086.txt",
    "score": 0.7045147991663102
  },
  {
    "document1": "document0040.txt",
    "document2": "document0087.txt",
    "score": 0.705850416196473
  },
  {
    "document1": "document0040.txt",
    "document2": "document0089.txt",
    "score": 0.7082271070421202
  },
  {
    "document1": "document0040.txt",
    "document2": "document0090.txt",
    "score": 0.7111145540948556
  },
  {
    "document1": "document0040.txt",
    "document2": "document0091.txt",
    "score": 0.7092613219925107
  },
  {
    "document1": "document0040.txt",
    "document2": "document0097.txt",
    "score": 0.713811092251811
  },
  {
    "document1": "document0040.txt",
    "document2": "document0099.txt",
    "score": 0.7131360531862491
  },
  {
    "document1": "document0040.txt",
    "document2": "document0100.txt",
    "score": 0.7127147683929247
  },
  {
    "document1": "document0041.txt",
    "document2": "document0046.txt",
    "score": 0.7129390811577624
  },
  {
    "document1": "document0041.txt",
    "document2": "document0057.txt",
    "score": 0.7049528771889368
  },
  {
    "document1": "document0041.txt",
    "document2": "document0060.txt",
    "score": 0.7030925189722955
  },
  {
    "document1": "document0041.txt",
    "document2": "document0062.txt",
    "score": 0.7007583652500589
  },
  {
    "document1": "document0041.txt",
    "document2": "document0067.txt",
    "score": 0.7117336097664675
  },
  {
    "document1": "document0041.txt",
    "document2": "document0073.txt",
    "score": 0.7125558488143744
  },
  {
    "document1": "document0041.txt",
    "document2": "document0074.txt",
    "score": 0.7130348415403277
  },
  {
    "document1": "document0041.txt",
    "document2": "document0082.txt",
    "score": 0.7091707504661529
  },
  {
    "document1": "document0041.txt",
    "document2": "document0084.txt",
    "score": 0.7067709306493346
  },
  {
    "document1": "document0041.txt",
    "document2": "document0086.txt",
    "score": 0.7005913599579492
  },
  {
    "document1": "document0042.txt",
    "document2": "document0051.txt",
    "score": 0.7112886595235309
  },
  {
    "document1": "document0042.txt",
    "document2": "document0053.txt",
    "score": 0.7133058499895015
  },
  {
    "document1": "document0042.txt",
    "document2": "document0061.txt",
    "score": 0.70511612108363
  },
  {
    "document1": "document0042.txt",
    "document2": "document0065.txt",
    "score": 0.7056716629596648
  },
  {
    "document1": "document0042.txt",
    "document2": "document0068.txt",
    "score": 0.7003439484994884
  },
  {
    "document1": "document0042.txt",
    "document2": "document0070.txt",
    "score": 0.7091427973869132
  },
  {
    "document1": "document0042.txt",
    "document2": "document0085.txt",
    "score": 0.7142103864325547
  },
  {
    "document1": "document0042.txt",
    "document2": "document0095.txt",
    "score": 0.7075537323741785
  },
  {
    "document1": "document0043.txt",
    "document2": "document0061.txt",
    "score": 0.7068789488966053
  },
  {
    "document1": "document0043.txt",
    "document2": "document0095.txt",
    "score": 0.7044470873205515
  },
  {
    "document1": "document0044.txt",
    "document2": "document0052.txt",
    "score": 0.7082097227211774
  },
  {
    "document1": "document0044.txt",
    "document2": "document0054.txt",
    "score": 0.7030362480921934
  },
  {
    "document1": "document0044.txt",
    "document2": "document0055.txt",
    "score": 0.7010118736674884
  },
  {
    "document1": "document0044.txt",
    "document2": "document0069.txt",
    "score": 0.7058038646010217
  },
  {
    "document1": "document0044.txt",
    "document2": "document0076.txt",
    "score": 0.7053279959250531
  },
  {
    "document1": "document0044.txt",
    "document2": "document0081.txt",
    "score": 0.7060599840413335
  },
  {
    "document1": "document0044.txt",
    "document2": "document0086.txt",
    "score": 0.7049362565320006
  },
  {
    "document1": "document0044.txt",
    "document2": "document0087.txt",
    "score": 0.706273869406296
  },
  {
    "document1": "document0044.txt",
    "document2": "document0089.txt",
    "score": 0.7086540732298389
  },
  {
    "document1": "document0044.txt",
    "document2": "document0090.txt",
    "score": 0.7115457208545952
  },
  {
    "document1": "document0044.txt",
    "document2": "document0091.txt",
    "score": 0.7096898012778252
  },
  {
    "document1": "document0044.txt",
    "document2": "document0097.txt",
    "score": 0.7133766870293755
  },
  {
    "document1": "document0044.txt",
    "document2": "document0099.txt",
    "score": 0.7135701161290204
  },
  {
    "document1": "document0044.txt",
    "document2": "document0100.txt",
    "score": 0.7122819246302875
  },
  {
    "document1": "document0045.txt",
    "document2": "document0048.txt",
    "score": 0.7063274965921088
  },
  {
    "document1": "document0045.txt",
    "document2": "document0060.txt",
    "score": 0.7017437252542167
  },
  {
    "document1": "document0045.txt",
    "document2": "document0062.txt",
    "score": 0.7040862869190443
  },
  {
    "document1": "document0045.txt",
    "document2": "document0072.txt",
    "score": 0.712140715195584
  },
  {
    "document1": "document0045.txt",
    "document2": "document0075.txt",
    "score": 0.7102806032479877
  },
  {
    "document1": "document0045.txt",
    "document2": "document0079.txt",
    "score": 0.7135001325736713
  },
  {
    "document1": "document0045.txt",
    "document2": "document0080.txt",
    "score": 0.7081568230930275
  },
  {
    "document1": "document0045.txt",
    "document2": "document0092.txt",
    "score": 0.7078964528736591
  },
  {
    "document1": "document0045.txt",
    "document2": "document0094.txt",
    "score": 0.7148062991361036
  },
  {
    "document1": "document0045.txt",
    "document2": "document0098.txt",
    "score": 0.7116776491533318
  },
  {
    "document1": "document0046.txt",
    "document2": "document0057.txt",
    "score": 0.70294772833061
  },
  {
    "document1": "document0046.txt",
    "document2": "document0060.txt",
    "score": 0.7011007557489739
  },
  {
    "document1": "document0046.txt",
    "document2": "document0067.txt",
    "score": 0.7138004697620828
  },
  {
    "document1": "document0046.txt",
    "document2": "document0069.txt",
    "score": 0.7017217654951033
  },
  {
    "document1": "document0046.txt",
    "document2": "document0073.txt",
    "score": 0.7146283141813361
  },
  {
    "document1": "document0046.txt",
    "document2": "document0074.txt",
    "score": 0.714917769262996
  },
  {
    "document1": "document0046.txt",
    "document2": "document0081.txt",
    "score": 0.701469600887928
  },
  {
    "document1": "document0046.txt",
    "document2": "document0082.txt",
    "score": 0.7071357755148467
  },
  {
    "document1": "document0046.txt",
    "document2": "document0084.txt",
    "score": 0.7088033366533963
  },
  {
    "document1": "document0046.txt",
    "document2": "document0086.txt",
    "score": 0.7025794067691242
  },
  {
    "document1": "document0046.txt",
    "document2": "document0087.txt",
    "score": 0.7012593702027449
  },
  {
    "document1": "document0047.txt",
    "document2": "document0050.txt",
    "score": 0.7068461839176
  },
  {
    "document1": "document0047.txt",
    "document2": "document0078.txt",
    "score": 0.7064181470416296
  },
  {
    "document1": "document0048.txt",
    "document2": "document0057.txt",
    "score": 0.7083972571841035
  },
  {
    "document1": "document0048.txt",
    "document2": "document0060.txt",
    "score": 0.710292517311196
  },
  {
    "document1": "document0048.txt",
    "document2": "document0062.txt",
    "score": 0.7127060226833692
  },
  {
    "document1": "document0048.txt",
    "document2": "document0072.txt",
    "score": 0.7035375077711457
  },
  {
    "document1": "document0048.txt",
    "document2": "document0075.txt",
    "score": 0.7109980261412104
  },
  {
    "document1": "document0048.txt",
    "document2": "document0079.txt",
    "score": 0.7048572709347786
  },
  {
    "document1": "document0048.txt",
    "document2": "document0082.txt",
    "score": 0.7041906795448539
  },
  {
    "document1": "document0048.txt",
    "document2": "document0092.txt",
    "score": 0.7134072814562198
  },
  {
    "document1": "document0048.txt",
    "document2": "document0094.txt",
    "score": 0.7065295009513105
  },
  {
    "document1": "document0048.txt",
    "document2": "document0098.txt",
    "score": 0.7096041629053026
  },
  {
    "document1": "document0049.txt",
    "document2": "document0051.txt",
    "score": 0.7020197980299095
  },
  {
    "document1": "document0049.txt",
    "document2": "document0053.txt",
    "score": 0.7000803282427546
  },
  {
    "document1": "document0049.txt",
    "document2": "document0056.txt",
    "score": 0.7142592655189273
  },
  {
    "document1": "document0049.txt",
    "document2": "document0065.txt",
    "score": 0.7075648841254191
  },
  {
    "document1": "document0049.txt",
    "document2": "document0066.txt",
    "score": 0.714428953767248
  },
  {
    "document1": "document0049.txt",
    "document2": "document0068.txt",
    "score": 0.713030025075636
  },
  {
    "document1": "document0049.txt",
    "document2": "document0070.txt",
    "score": 0.7041127208967412
  },
  {
    "document1": "document0049.txt",
    "document2": "document0096.txt",
    "score": 0.703473227452613
  },
  {
    "document1": "document0050.txt",
    "document2": "document0078.txt",
    "score": 0.7145742043560092
  },
  {
    "document1": "document0051.txt",
    "document2": "document0053.txt",
    "score": 0.7129856489116366
  },
  {
    "document1": "document0051.txt",
    "document2": "document0056.txt",
    "score": 0.70274357560426
  },
  {
    "document1": "document0051.txt",
    "document2": "document0061.txt",
    "score": 0.7015146587168098
  },
  {
    "document1": "document0051.txt",
    "document2": "document0065.txt",
    "score": 0.7093267758325159
  },
  {
    "document1": "document0051.txt",
    "document2": "document0066.txt",
    "score": 0.7014601811809036
  },
  {
    "document1": "document0051.txt",
    "document2": "document0068.txt",
    "score": 0.7039300664778497
  },
  {
    "document1": "document0051.txt",
    "document2": "document0070.txt",
    "score": 0.7128416925030956
  },
  {
    "document1": "document0051.txt",
    "document2": "document0085.txt",
    "score": 0.710494694409864
  },
  {
    "document1": "document0051.txt",
    "document2": "document0095.txt",
    "score": 0.7039210529754715
  },
  {
    "document1": "document0052.txt",
    "document2": "document0054.txt",
    "score": 0.7097200605548524
  },
  {
    "document1": "document0052.txt",
    "document2": "document0055.txt",
    "score": 0.7076474456127255
  },
  {
    "document1": "document0052.txt",
    "document2": "document0076.txt",
    "score": 0.7120657154564097
  },
  {
    "document1": "document0052.txt",
    "document2": "document0089.txt",
    "score": 0.7019950010560063
  },
  {
    "document1": "document0052.txt",
    "document2": "document0090.txt",
    "score": 0.704819888079296
  },
  {
    "document1": "document0052.txt",
    "document2": "document0091.txt",
    "score": 0.7030066890207016
  },
  {
    "document1": "document0052.txt",
    "document2": "document0097.txt",
    "score": 0.7098191512355043
  },
  {
    "document1": "document0052.txt",
    "document2": "document0099.txt",
    "score": 0.7067982125807455
  },
  {
    "document1": "document0052.txt",
    "document2": "document0100.txt",
    "score": 0.7109049474591693
  },
  {
    "document1": "document0053.txt",
    "document2": "document0056.txt",
    "score": 0.700798968986967
  },
  {
    "document1": "document0053.txt",
    "document2": "document0061.txt",
    "score": 0.7034643605690661
  },
  {
    "document1": "document0053.txt",
    "document2": "document0065.txt",
    "score": 0.7073363986940194
  },
  {
    "document1": "document0053.txt",
    "document2": "document0068.txt",
    "score": 0.7019770833925605
  },
  {
    "document1": "document0053.txt",
    "document2": "document0070.txt",
    "score": 0.710827596043756
  },
  {
    "document1": "document0053.txt",
    "document2": "document0085.txt",
    "score": 0.7125065512871505
  },
  {
    "document1": "document0053.txt",
    "document2": "document0095.txt",
    "score": 0.705887735508723
  },
  {
    "document1": "document0054.txt",
    "document2": "document0055.txt",
    "score": 0.7129046661458607
  },
  {
    "document1": "document0054.txt",
    "document2": "document0076.txt",
    "score": 0.7126455884276124
  },
  {
    "document1": "document0054.txt",
    "document2": "document0096.txt",
    "score": 0.7033090331822414
  },
  {
    "document1": "document0054.txt",
    "document2": "document0097.txt",
    "score": 0.7046167084047332
  },
  {
    "document1": "document0054.txt",
    "document2": "document0099.txt",
    "score": 0.7016503642750845
  },
  {
    "document1": "document0054.txt",
    "document2": "document0100.txt",
    "score": 0.7056831139357183
  },
  {
    "document1": "document0055.txt",
    "document2": "document0076.txt",
    "score": 0.7105524505874551
  },
  {
    "document1": "document0055.txt",
    "document2": "document0096.txt",
    "score": 0.7053503192234836
  },
  {
    "document1": "document0055.txt",
    "document2": "document0097.txt",
    "score": 0.7025807599164331
  },
  {
    "document1": "document0055.txt",
    "document2": "document0100.txt",
    "score": 0.7036394138950589
  },
  {
    "document1": "document0056.txt",
    "document2": "document0065.txt",
    "score": 0.7083030390296442
  },
  {
    "document1": "document0056.txt",
    "document2": "document0066.txt",
    "score": 0.7136755010635041
  },
  {
    "document1": "document0056.txt",
    "document2": "document0068.txt",
    "score": 0.7137818894940304
  },
  {
    "document1": "document0056.txt",
    "document2": "document0070.txt",
    "score": 0.7048419793001385
  },
  {
    "document1": "document0056.txt",
    "document2": "document0096.txt",
    "score": 0.7027475367264929
  },
  {
    "document1": "document0057.txt",
    "document2": "document0060.txt",
    "score": 0.7130889500242727
  },
  {
    "document1": "document0057.txt",
    "document2": "document0062.txt",
    "score": 0.7106723773309077
  },
  {
    "document1": "document0057.txt",
    "document2": "document0067.txt",
    "score": 0.7017832635328757
  },
  {
    "document1": "document0057.txt",
    "document2": "document0073.txt",
    "score": 0.702577501630025
  },
  {
    "document1": "document0057.txt",
    "document2": "document0074.txt",
    "score": 0.703040243416469
  },
  {
    "document1": "document0057.txt",
    "document2": "document0075.txt",
    "score": 0.7044697250521953
  },
  {
    "document1": "document0057.txt",
    "document2": "document0082.txt",
    "score": 0.7107126039291431
  },
  {
    "document1": "document0057.txt",
    "document2": "document0092.txt",
    "score": 0.7068255794543874
  },
  {
    "document1": "document0057.txt",
    "document2": "document0094.txt",
    "score": 0.7001022385943171
  },
  {
    "document1": "document0057.txt",
    "document2": "document0098.txt",
    "score": 0.7031071028738259
  },
  {
    "document1": "document0058.txt",
    "document2": "document0063.txt",
    "score": 0.7092857390614358
  },
  {
    "document1": "document0058.txt",
    "document2": "document0064.txt",
    "score": 0.7060728964202331
  },
  {
    "document1": "document0058.txt",
    "document2": "document0071.txt",
    "score": 0.7145257740925316
  },
  {
    "document1": "document0058.txt",
    "document2": "document0083.txt",
    "score": 0.7085432222754035
  },
  {
    "document1": "document0058.txt",
    "document2": "document0093.txt",
    "score": 0.7129296505316325
  },
  {
    "document1": "document0059.txt",
    "document2": "document0063.txt",
    "score": 0.7028288216871973
  },
  {
    "document1": "document0059.txt",
    "document2": "document0064.txt",
    "score": 0.7060050514915862
  },
  {
    "document1": "document0059.txt",
    "document2": "document0083.txt",
    "score": 0.7035565620443899
  },
  {
    "document1": "document0060.txt",
    "document2": "document0062.txt",
    "score": 0.7125822662113084
  },
  {
    "document1": "document0060.txt",
    "document2": "document0073.txt",
    "score": 0.7007330169513721
  },
  {
    "document1": "document0060.txt",
    "document2": "document0074.txt",
    "score": 0.7011926499340027
  },
  {
    "document1": "document0060.txt",
    "document2": "document0075.txt",
    "score": 0.7063392497715861
  },
  {
    "document1": "document0060.txt",
    "document2": "document0079.txt",
    "score": 0.7002975258500347
  },
  {
    "document1": "document0060.txt",
    "document2": "document0082.txt",
    "score": 0.708814644577516
  },
  {
    "document1": "document0060.txt",
    "document2": "document0092.txt",
    "score": 0.7087106137211959
  },
  {
    "document1": "document0060.txt",
    "document2": "document0094.txt",
    "score": 0.70194244388536
  },
  {
    "document1": "document0060.txt",
    "document2": "document0098.txt",
    "score": 0.7049675585417912
  },
  {
    "document1": "document0061.txt",
    "document2": "document0085.txt",
    "score": 0.7058954994304453
  },
  {
    "document1": "document0061.txt",
    "document2": "document0095.txt",
    "score": 0.7125144924608199
  },
  {
    "document1": "document0062.txt",
    "document2": "document0072.txt",
    "score": 0.7013185266656311
  },
  {
    "document1": "document0062.txt",
    "document2": "document0075.txt",
    "score": 0.7087203996003052
  },
  {
    "document1": "document0062.txt",
    "document2": "document0079.txt",
    "score": 0.70262773125787
  },
  {
    "document1": "document0062.txt",
    "document2": "document0082.txt",
    "score": 0.7064327206858477
  },
  {
    "document1": "document0062.txt",
    "document2": "document0092.txt",
    "score": 0.7111112665268168
  },
  {
    "document1": "document0062.txt",
    "document2": "document0094.txt",
    "score": 0.7042866955087532
  },
  {
    "document1": "document0062.txt",
    "document2": "document0098.txt",
    "score": 0.7073372990852193
  },
  {
    "document1": "document0063.txt",
    "document2": "document0064.txt",
    "score": 0.7117390686972596
  },
  {
    "document1": "document0063.txt",
    "document2": "document0071.txt",
    "score": 0.709765695380309
  },
  {
    "document1": "document0063.txt",
    "document2": "document0083.txt",
    "score": 0.7142573606159525
  },
  {
    "document1": "document0063.txt",
    "document2": "document0093.txt",
    "score": 0.7072407103376125
  },
  {
    "document1": "document0064.txt",
    "document2": "document0071.txt",
    "score": 0.7065475549062133
  },
  {
    "document1": "document0064.txt",
    "document2": "document0083.txt",
    "score": 0.7124896306628244
  },
  {
    "document1": "document0064.txt",
    "document2": "document0093.txt",
    "score": 0.7040506089281022
  },
  {
    "document1": "document0065.txt",
    "document2": "document0066.txt",
    "score": 0.7069941088468799
  },
  {
    "document1": "document0065.txt",
    "document2": "document0068.txt",
    "score": 0.709512965378385
  },
  {
    "document1": "document0065.txt",
    "document2": "document0070.txt",
    "score": 0.7114739754361035
  },
  {
    "document1": "document0065.txt",
    "document2": "document0085.txt",
    "score": 0.7048929001414118
  },
  {
    "document1": "document0066.txt",
    "document2": "document0068.txt",
    "score": 0.7124486053053352
  },
  {
    "document1": "document0066.txt",
    "document2": "document0070.txt",
    "score": 0.7035488508248697
  },
  {
    "document1": "document0066.txt",
    "document2": "document0096.txt",
    "score": 0.7040369444059573
  },
  {
    "document1": "document0067.txt",
    "document2": "document0069.txt",
    "score": 0.7028859693562746
  },
  {
    "document1": "document0067.txt",
    "document2": "document0073.txt",
    "score": 0.7141852691680053
  },
  {
    "document1": "document0067.txt",
    "document2": "document0074.txt",
    "score": 0.713704468883022
  },
  {
    "document1": "document0067.txt",
    "document2": "document0081.txt",
    "score": 0.7026327338705098
  },
  {
    "document1": "document0067.txt",
    "document2": "document0082.txt",
    "score": 0.7059538272949095
  },
  {
    "document1": "document0067.txt",
    "document2": "document0084.txt",
    "score": 0.7099969861325344
  },
  {
    "document1": "document0067.txt",
    "document2": "document0086.txt",
    "score": 0.7037472414518711
  },
  {
    "document1": "document0067.txt",
    "document2": "document0087.txt",
    "score": 0.7024216092321974
  },
  {
    "document1": "document0067.txt",
    "document2": "document0089.txt",
    "score": 0.7000935501821084
  },
  {
    "document1": "document0068.txt",
    "document2": "document0070.txt",
    "score": 0.7060374057291533
  },
  {
    "document1": "document0068.txt",
    "document2": "document0096.txt",
    "score": 0.7015661069104829
  },
  {
    "document1": "document0069.txt",
    "document2": "document0073.txt",
    "score": 0.7020908411297544
  },
  {
    "document1": "document0069.txt",
    "document2": "document0074.txt",
    "score": 0.7016296928426531
  },
  {
    "document1": "document0069.txt",
    "document2": "document0081.txt",
    "score": 0.7147501824663819
  },
  {
    "document1": "document0069.txt",
    "document2": "document0084.txt",
    "score": 0.707781580568649
  },
  {
    "document1": "document0069.txt",
    "document2": "document0086.txt",
    "score": 0.7141190993385851
  },
  {
    "document1": "document0069.txt",
    "document2": "document0087.txt",
    "score": 0.7145300981973717
  },
  {
    "document1": "document0069.txt",
    "document2": "document0089.txt",
    "score": 0.7121024563656444
  },
  {
    "document1": "document0069.txt",
    "document2": "document0090.txt",
    "score": 0.7092054011272432
  },
  {
    "document1": "document0069.txt",
    "document2": "document0091.txt",
    "score": 0.7110582819599554
  },
  {
    "document1": "document0069.txt",
    "document2": "document0097.txt",
    "score": 0.7042167166335328
  },
  {
    "document1": "document0069.txt",
    "document2": "document0099.txt",
    "score": 0.7072104846444168
  },
  {
    "document1": "document0069.txt",
    "document2": "document0100.txt",
    "score": 0.7031558638663583
  },
  {
    "document1": "document0070.txt",
    "document2": "document0085.txt",
    "score": 0.708354579634522
  },
  {
    "document1": "document0070.txt",
    "document2": "document0095.txt",
    "score": 0.7018295743402979
  },
  {
    "document1": "document0071.txt",
    "document2": "document0083.txt",
    "score": 0.7090219632998978
  },
  {
    "document1": "document0071.txt",
    "document2": "document0093.txt",
    "score": 0.7124445858802961
  },
  {
    "document1": "document0072.txt",
    "document2": "document0075.txt",
    "score": 0.7074520992857337
  },
  {
    "document1": "document0072.txt",
    "document2": "document0079.txt",
    "score": 0.7136479994245267
  },
  {
    "document1": "document0072.txt",
    "document2": "document0080.txt",
    "score": 0.7109921646113389
  },
  {
    "document1": "document0072.txt",
    "document2": "document0092.txt",
    "score": 0.7050910711161218
  },
  {
    "document1": "document0072.txt",
    "document2": "document0094.txt",
    "score": 0.7119348105557566
  },
  {
    "document1": "document0072.txt",
    "document2": "document0098.txt",
    "score": 0.7088357484280436
  },
  {
    "document1": "document0073.txt",
    "document2": "document0074.txt",
    "score": 0.71453205459178
  },
  {
    "document1": "document0073.txt",
    "document2": "document0081.txt",
    "score": 0.7018383362799439
  },
  {
    "document1": "document0073.txt",
    "document2": "document0082.txt",
    "score": 0.7067600030507091
  },
  {
    "document1": "document0073.txt",
    "document2": "document0084.txt",
    "score": 0.7091817693348365
  },
  {
    "document1": "document0073.txt",
    "document2": "document0086.txt",
    "score": 0.7029496360261818
  },
  {
    "document1": "document0073.txt",
    "document2": "document0087.txt",
    "score": 0.7016278215681773
  },
  {
    "document1": "document0074.txt",
    "document2": "document0081.txt",
    "score": 0.7013776132238665
  },
  {
    "document1": "document0074.txt",
    "document2": "document0082.txt",
    "score": 0.7072296745404565
  },
  {
    "document1": "document0074.txt",
    "document2": "document0084.txt",
    "score": 0.7087089265104947
  },
  {
    "document1": "document0074.txt",
    "document2": "document0086.txt",
    "score": 0.7024870459521746
  },
  {
    "document1": "document0074.txt",
    "document2": "document0087.txt",
    "score": 0.7011674534845986
  },
  {
    "document1": "document0075.txt",
    "document2": "document0079.txt",
    "score": 0.7087901617274491
  },
  {
    "document1": "document0075.txt",
    "document2": "document0080.txt",
    "score": 0.7035317961859501
  },
  {
    "document1": "document0075.txt",
    "document2": "document0082.txt",
    "score": 0.7003212789613718
  },
  {
    "document1": "document0075.txt",
    "document2": "document0092.txt",
    "score": 0.7125921803604277
  },
  {
    "document1": "document0075.txt",
    "document2": "document0094.txt",
    "score": 0.7104853711454401
  },
  {
    "document1": "document0075.txt",
    "document2": "document0098.txt",
    "score": 0.7136016729596174
  },
  {
    "document1": "document0076.txt",
    "document2": "document0090.txt",
    "score": 0.7019724106869027
  },
  {
    "document1": "document0076.txt",
    "document2": "document0091.txt",
    "score": 0.7001778022560972
  },
  {
    "document1": "document0076.txt",
    "document2": "document0096.txt",
    "score": 0.7010338519925744
  },
  {
    "document1": "document0076.txt",
    "document2": "document0097.txt",
    "score": 0.70692139780086
  },
  {
    "document1": "document0076.txt",
    "document2": "document0099.txt",
    "score": 0.7039306662535911
  },
  {
    "document1": "document0076.txt",
    "document2": "document0100.txt",
    "score": 0.7079964680141034
  },
  {
    "document1": "document0079.txt",
    "document2": "document0080.txt",
    "score": 0.709644041383553
  },
  {
    "document1": "document0079.txt",
    "document2": "document0092.txt",
    "score": 0.7064181470416296
  },
  {
    "document1": "document0079.txt",
    "document2": "document0094.txt",
    "score": 0.7132933032100107
  },
  {
    "document1": "document0079.txt",
    "document2": "document0098.txt",
    "score": 0.7101801773638631
  },
  {
    "document1": "document0080.txt",
    "document2": "document0092.txt",
    "score": 0.7012034483996129
  },
  {
    "document1": "document0080.txt",
    "document2": "document0093.txt",
    "score": 0.7010843768654379
  },
  {
    "document1": "document0080.txt",
    "document2": "document0094.txt",
    "score": 0.7079536739422162
  },
  {
    "document1": "document0080.txt",
    "document2": "document0098.txt",
    "score": 0.7048964971819577
  },
  {
    "document1": "document0081.txt",
    "document2": "document0084.txt",
    "score": 0.7075239189430835
  },
  {
    "document1": "document0081.txt",
    "document2": "document0086.txt",
    "score": 0.71385589759966
  },
  {
    "document1": "document0081.txt",
    "document2": "document0087.txt",
    "score": 0.7147938768936662
  },
  {
    "document1": "document0081.txt",
    "document2": "document0089.txt",
    "score": 0.7123641458105708
  },
  {
    "document1": "document0081.txt",
    "document2": "document0090.txt",
    "score": 0.7094645551234693
  },
  {
    "document1": "document0081.txt",
    "document2": "document0091.txt",
    "score": 0.7113190628201408
  },
  {
    "document1": "document0081.txt",
    "document2": "document0097.txt",
    "score": 0.704471399216566
  },
  {
    "document1": "document0081.txt",
    "document2": "document0099.txt",
    "score": 0.707467866416838
  },
  {
    "document1": "document0081.txt",
    "document2": "document0100.txt",
    "score": 0.7034095787139769
  },
  {
    "document1": "document0082.txt",
    "document2": "document0084.txt",
    "score": 0.7010897532458652
  },
  {
    "document1": "document0082.txt",
    "document2": "document0092.txt",
    "score": 0.7026421093845521
  },
  {
    "document1": "document0083.txt",
    "document2": "document0093.txt",
    "score": 0.7065034111906714
  },
  {
    "document1": "document0084.txt",
    "document2": "document0086.txt",
    "score": 0.7086578567453788
  },
  {
    "document1": "document0084.txt",
    "document2": "document0087.txt",
    "score": 0.7073090991474248
  },
  {
    "document1": "document0084.txt",
    "document2": "document0089.txt",
    "score": 0.7049399912928439
  },
  {
    "document1": "document0084.txt",
    "document2": "document0090.txt",
    "score": 0.7021138892732992
  },
  {
    "document1": "document0084.txt",
    "document2": "document0091.txt",
    "score": 0.7039212532026032
  },
  {
    "document1": "document0084.txt",
    "document2": "document0099.txt",
    "score": 0.7001685171282378
  },
  {
    "document1": "document0085.txt",
    "document2": "document0095.txt",
    "score": 0.7083397800688642
  },
  {
    "document1": "document0086.txt",
    "document2": "document0087.txt",
    "score": 0.7136364519458546
  },
  {
    "document1": "document0086.txt",
    "document2": "document0089.txt",
    "score": 0.7112159141977189
  },
  {
    "document1": "document0086.txt",
    "document2": "document0090.txt",
    "score": 0.7083274786722831
  },
  {
    "document1": "document0086.txt",
    "document2": "document0091.txt",
    "score": 0.7101748288825674
  },
  {
    "document1": "document0086.txt",
    "document2": "document0097.txt",
    "score": 0.703353991643448
  },
  {
    "document1": "document0086.txt",
    "document2": "document0099.txt",
    "score": 0.7063385862099091
  },
  {
    "document1": "document0086.txt",
    "document2": "document0100.txt",
    "score": 0.7022964274048775
  },
  {
    "document1": "document0087.txt",
    "document2": "document0089.txt",
    "score": 0.7125826759012015
  },
  {
    "document1": "document0087.txt",
    "document2": "document0090.txt",
    "score": 0.7096809710496733
  },
  {
    "document1": "document0087.txt",
    "document2": "document0091.txt",
    "score": 0.7115368353143543
  },
  {
    "document1": "document0087.txt",
    "document2": "document0097.txt",
    "score": 0.7046840862858066
  },
  {
    "document1": "document0087.txt",
    "document2": "document0099.txt",
    "score": 0.7076828044874205
  },
  {
    "document1": "document0087.txt",
    "document2": "document0100.txt",
    "score": 0.7036214586935431
  },
  {
    "document1": "document0089.txt",
    "document2": "document0090.txt",
    "score": 0.7120891137976919
  },
  {
    "document1": "document0089.txt",
    "document2": "document0091.txt",
    "score": 0.7139599493462183
  },
  {
    "document1": "document0089.txt",
    "document2": "document0097.txt",
    "score": 0.7070510553201873
  },
  {
    "document1": "document0089.txt",
    "document2": "document0099.txt",
    "score": 0.7100746325522478
  },
  {
    "document1": "document0089.txt",
    "document2": "document0100.txt",
    "score": 0.7059795119882843
  },
  {
    "document1": "document0090.txt",
    "document2": "document0091.txt",
    "score": 0.7131368710000376
  },
  {
    "document1": "document0090.txt",
    "document2": "document0097.txt",
    "score": 0.709926874906658
  },
  {
    "document1": "document0090.txt",
    "document2": "document0099.txt",
    "score": 0.7129801757056714
  },
  {
    "document1": "document0090.txt",
    "document2": "document0100.txt",
    "score": 0.7088446646256135
  },
  {
    "document1": "document0091.txt",
    "document2": "document0097.txt",
    "score": 0.7080810822756267
  },
  {
    "document1": "document0091.txt",
    "document2": "document0099.txt",
    "score": 0.7111153664445565
  },
  {
    "document1": "document0091.txt",
    "document2": "document0100.txt",
    "score": 0.7070056973667018
  },
  {
    "document1": "document0092.txt",
    "document2": "document0094.txt",
    "score": 0.7080995619301567
  },
  {
    "document1": "document0092.txt",
    "document2": "document0098.txt",
    "score": 0.7111908727916666
  },
  {
    "document1": "document0094.txt",
    "document2": "document0098.txt",
    "score": 0.7118833778470144
  },
  {
    "document1": "document0097.txt",
    "document2": "document0099.txt",
    "score": 0.7119403552907411
  },
  {
    "document1": "document0097.txt",
    "document2": "document0100.txt",
    "score": 0.7139135232945198
  },
  {
    "document1": "document0099.txt",
    "document2": "document0100.txt",
    "score": 0.7108507863284729
  }
]